Workbook

Sheet Sheet1
A1: No. | B1: company | C1: 業種 | D1: share | E1: Op_2021 | F1: Op_2022 | G1: Op_2023 | H1: Op_2024 | I1: Op_2025 | J1: Op_2026 | K1: Op_2027 | L1: FCF_2021 | M1: FCF_2022 | N1: FCF_2023 | O1: FCF_2024 | P1: FCF_2025 | Q1: ROE_2021 | R1: ROE_2022 | S1: ROE_2023 | T1: ROE_2024 | U1: ROE_2025 | V1: ticker | W1: PER | X1: PBR | Y1: 市場区分
A2: 1 | B2: =_xlfn.XLOOKUP('Sheet1 (4)'!AB8,'Sheet1 (3)'!B:B,'Sheet1 (3)'!C:C,"",0) -> Ａｎｄ Ｄｏホールディングス | C2: =_xlfn.XLOOKUP('Sheet1 (4)'!AB8,'Sheet1 (3)'!B:B,'Sheet1 (3)'!F:F,"",0) -> 不動産業 | D2: =ROUND('Sheet1 (4)'!E8/100000000,2) -> 0.2 | E2: =ROUND('Sheet1 (4)'!F8/100,2) -> 25.89 | F2: =ROUND('Sheet1 (4)'!G8/100,2) -> 28.72 | G2: =ROUND('Sheet1 (4)'!H8/100,2) -> 31.77 | H2: =ROUND('Sheet1 (4)'!I8/100,2) -> 35.88 | I2: =ROUND('Sheet1 (4)'!J8/100,2) -> 26.21 | J2: =ROUND('Sheet1 (4)'!K8/100,2) -> #VALUE! | K2: =ROUND('Sheet1 (4)'!L8/100,2) -> #VALUE! | L2: =ROUND(('Sheet1 (4)'!M8+'Sheet1 (4)'!R8)/100,2) -> -25.93 | M2: =ROUND(('Sheet1 (4)'!N8+'Sheet1 (4)'!S8)/100,2) -> -88.96 | N2: =ROUND(('Sheet1 (4)'!O8+'Sheet1 (4)'!T8)/100,2) -> -191.21 | O2: =ROUND(('Sheet1 (4)'!P8+'Sheet1 (4)'!U8)/100,2) -> 61.31 | P2: =ROUND(('Sheet1 (4)'!Q8+'Sheet1 (4)'!V8)/100,2) -> 67.87 | Q2: =ROUND('Sheet1 (4)'!W8/100,2) -> 0.13 | R2: =ROUND('Sheet1 (4)'!X8/100,2) -> 0.15 | S2: =ROUND('Sheet1 (4)'!Y8/100,2) -> 0.15 | T2: =ROUND('Sheet1 (4)'!Z8/100,2) -> 0.15 | U2: =ROUND('Sheet1 (4)'!AA8/100,2) -> 0.13 | V2: ='Sheet1 (4)'!AB8&".T" -> 3457.T | W2: =ROUND('Sheet1 (4)'!AC8,2) -> 8.89 | X2: =ROUND('Sheet1 (4)'!AD8,2) -> 1.14 | Y2: =_xlfn.XLOOKUP('Sheet1 (4)'!AB8,'Sheet1 (3)'!B:B,'Sheet1 (3)'!D:D,"",0) -> プライム
A3: 2 | B3: =_xlfn.XLOOKUP('Sheet1 (4)'!AB9,'Sheet1 (3)'!B:B,'Sheet1 (3)'!C:C,"",0) -> スリー・ディー・マトリックス | C3: =_xlfn.XLOOKUP('Sheet1 (4)'!AB9,'Sheet1 (3)'!B:B,'Sheet1 (3)'!F:F,"",0) -> 精密機器 | D3: =ROUND('Sheet1 (4)'!E9/100000000,2) -> 1.14 | E3: =ROUND('Sheet1 (4)'!F9/100,2) -> -26.49 | F3: =ROUND('Sheet1 (4)'!G9/100,2) -> -27.36 | G3: =ROUND('Sheet1 (4)'!H9/100,2) -> -31.58 | H3: =ROUND('Sheet1 (4)'!I9/100,2) -> -21.17 | I3: =ROUND('Sheet1 (4)'!J9/100,2) -> -11.56 | J3: =ROUND('Sheet1 (4)'!K9/100,2) -> #VALUE! | K3: =ROUND('Sheet1 (4)'!L9/100,2) -> #VALUE! | L3: =ROUND(('Sheet1 (4)'!M9+'Sheet1 (4)'!R9)/100,2) -> -34.09 | M3: =ROUND(('Sheet1 (4)'!N9+'Sheet1 (4)'!S9)/100,2) -> -29.82 | N3: =ROUND(('Sheet1 (4)'!O9+'Sheet1 (4)'!T9)/100,2) -> -46.66 | O3: =ROUND(('Sheet1 (4)'!P9+'Sheet1 (4)'!U9)/100,2) -> -19.28 | P3: =ROUND(('Sheet1 (4)'!Q9+'Sheet1 (4)'!V9)/100,2) -> -17.47 | Q3: =ROUND('Sheet1 (4)'!W9/100,2) -> -1.89 | R3: =ROUND('Sheet1 (4)'!X9/100,2) -> -1.21 | S3: =ROUND('Sheet1 (4)'!Y9/100,2) -> -2.47 | T3: =ROUND('Sheet1 (4)'!Z9/100,2) -> -0.58 | U3: =ROUND('Sheet1 (4)'!AA9/100,2) -> -1.95 | V3: ='Sheet1 (4)'!AB9&".T" -> 7777.T | W3: =ROUND('Sheet1 (4)'!AC9,2) -> #VALUE! | X3: =ROUND('Sheet1 (4)'!AD9,2) -> 13.56 | Y3: =_xlfn.XLOOKUP('Sheet1 (4)'!AB9,'Sheet1 (3)'!B:B,'Sheet1 (3)'!D:D,"",0) -> グロース
A4: 3 | B4: =_xlfn.XLOOKUP('Sheet1 (4)'!AB10,'Sheet1 (3)'!B:B,'Sheet1 (3)'!C:C,"",0) -> フォーシーズＨＤ | C4: =_xlfn.XLOOKUP('Sheet1 (4)'!AB10,'Sheet1 (3)'!B:B,'Sheet1 (3)'!F:F,"",0) -> 小売業 | D4: =ROUND('Sheet1 (4)'!E10/100000000,2) -> 0.11 | E4: =ROUND('Sheet1 (4)'!F10/100,2) -> -1.48 | F4: =ROUND('Sheet1 (4)'!G10/100,2) -> -1.19 | G4: =ROUND('Sheet1 (4)'!H10/100,2) -> -2.15 | H4: =ROUND('Sheet1 (4)'!I10/100,2) -> -1.26 | I4: =ROUND('Sheet1 (4)'!J10/100,2) -> -1.26 | J4: =ROUND('Sheet1 (4)'!K10/100,2) -> #VALUE! | K4: =ROUND('Sheet1 (4)'!L10/100,2) -> #VALUE! | L4: =ROUND(('Sheet1 (4)'!M10+'Sheet1 (4)'!R10)/100,2) -> -1.14 | M4: =ROUND(('Sheet1 (4)'!N10+'Sheet1 (4)'!S10)/100,2) -> -0.45 | N4: =ROUND(('Sheet1 (4)'!O10+'Sheet1 (4)'!T10)/100,2) -> -4.26 | O4: =ROUND(('Sheet1 (4)'!P10+'Sheet1 (4)'!U10)/100,2) -> -4.11 | P4: =ROUND(('Sheet1 (4)'!Q10+'Sheet1 (4)'!V10)/100,2) -> -4.11 | Q4: =ROUND('Sheet1 (4)'!W10/100,2) -> -0.28 | R4: =ROUND('Sheet1 (4)'!X10/100,2) -> -0.3 | S4: =ROUND('Sheet1 (4)'!Y10/100,2) -> -0.56 | T4: =ROUND('Sheet1 (4)'!Z10/100,2) -> -0.32 | U4: =ROUND('Sheet1 (4)'!AA10/100,2) -> -0.32 | V4: ='Sheet1 (4)'!AB10&".T" -> 3726.T | W4: =ROUND('Sheet1 (4)'!AC10,2) -> #VALUE! | X4: =ROUND('Sheet1 (4)'!AD10,2) -> 3.53 | Y4: =_xlfn.XLOOKUP('Sheet1 (4)'!AB10,'Sheet1 (3)'!B:B,'Sheet1 (3)'!D:D,"",0) -> スタンダード
A5: 4 | B5: =_xlfn.XLOOKUP('Sheet1 (4)'!AB11,'Sheet1 (3)'!B:B,'Sheet1 (3)'!C:C,"",0) -> エーアンドエーマテリアル | C5: =_xlfn.XLOOKUP('Sheet1 (4)'!AB11,'Sheet1 (3)'!B:B,'Sheet1 (3)'!F:F,"",0) -> ガラス・土石製品 | D5: =ROUND('Sheet1 (4)'!E11/100000000,2) -> 0.08 | E5: =ROUND('Sheet1 (4)'!F11/100,2) -> 14.72 | F5: =ROUND('Sheet1 (4)'!G11/100,2) -> 14.41 | G5: =ROUND('Sheet1 (4)'!H11/100,2) -> 14.91 | H5: =ROUND('Sheet1 (4)'!I11/100,2) -> 23.2 | I5: =ROUND('Sheet1 (4)'!J11/100,2) -> 19.17 | J5: =ROUND('Sheet1 (4)'!K11/100,2) -> #VALUE! | K5: =ROUND('Sheet1 (4)'!L11/100,2) -> #VALUE! | L5: =ROUND(('Sheet1 (4)'!M11+'Sheet1 (4)'!R11)/100,2) -> -1.39 | M5: =ROUND(('Sheet1 (4)'!N11+'Sheet1 (4)'!S11)/100,2) -> 0.87 | N5: =ROUND(('Sheet1 (4)'!O11+'Sheet1 (4)'!T11)/100,2) -> -10.11 | O5: =ROUND(('Sheet1 (4)'!P11+'Sheet1 (4)'!U11)/100,2) -> 35.8 | P5: =ROUND(('Sheet1 (4)'!Q11+'Sheet1 (4)'!V11)/100,2) -> -13.94 | Q5: =ROUND('Sheet1 (4)'!W11/100,2) -> 0.05 | R5: =ROUND('Sheet1 (4)'!X11/100,2) -> 0.06 | S5: =ROUND('Sheet1 (4)'!Y11/100,2) -> 0.06 | T5: =ROUND('Sheet1 (4)'!Z11/100,2) -> 0.15 | U5: =ROUND('Sheet1 (4)'!AA11/100,2) -> -0.01 | V5: ='Sheet1 (4)'!AB11&".T" -> 5391.T | W5: =ROUND('Sheet1 (4)'!AC11,2) -> 90.58 | X5: =ROUND('Sheet1 (4)'!AD11,2) -> 0.49 | Y5: =_xlfn.XLOOKUP('Sheet1 (4)'!AB11,'Sheet1 (3)'!B:B,'Sheet1 (3)'!D:D,"",0) -> スタンダード
A6: 5 | B6: =_xlfn.XLOOKUP('Sheet1 (4)'!AB12,'Sheet1 (3)'!B:B,'Sheet1 (3)'!C:C,"",0) -> Ａ＆Ｄホロンホールディングス | C6: =_xlfn.XLOOKUP('Sheet1 (4)'!AB12,'Sheet1 (3)'!B:B,'Sheet1 (3)'!F:F,"",0) -> 精密機器 | D6: =ROUND('Sheet1 (4)'!E12/100000000,2) -> 0.27 | E6: =ROUND('Sheet1 (4)'!F12/100,2) -> 44.05 | F6: =ROUND('Sheet1 (4)'!G12/100,2) -> 54.97 | G6: =ROUND('Sheet1 (4)'!H12/100,2) -> 74.76 | H6: =ROUND('Sheet1 (4)'!I12/100,2) -> 79.56 | I6: =ROUND('Sheet1 (4)'!J12/100,2) -> 88.13 | J6: =ROUND('Sheet1 (4)'!K12/100,2) -> 94.23 | K6: =ROUND('Sheet1 (4)'!L12/100,2) -> 98.9 | L6: =ROUND(('Sheet1 (4)'!M12+'Sheet1 (4)'!R12)/100,2) -> 29.72 | M6: =ROUND(('Sheet1 (4)'!N12+'Sheet1 (4)'!S12)/100,2) -> -6.13 | N6: =ROUND(('Sheet1 (4)'!O12+'Sheet1 (4)'!T12)/100,2) -> 27.32 | O6: =ROUND(('Sheet1 (4)'!P12+'Sheet1 (4)'!U12)/100,2) -> 51.94 | P6: =ROUND(('Sheet1 (4)'!Q12+'Sheet1 (4)'!V12)/100,2) -> 45.73 | Q6: =ROUND('Sheet1 (4)'!W12/100,2) -> 0.17 | R6: =ROUND('Sheet1 (4)'!X12/100,2) -> 0.16 | S6: =ROUND('Sheet1 (4)'!Y12/100,2) -> 0.19 | T6: =ROUND('Sheet1 (4)'!Z12/100,2) -> 0.15 | U6: =ROUND('Sheet1 (4)'!AA12/100,2) -> 0.16 | V6: ='Sheet1 (4)'!AB12&".T" -> 7745.T | W6: =ROUND('Sheet1 (4)'!AC12,2) -> 8.36 | X6: =ROUND('Sheet1 (4)'!AD12,2) -> 1.21 | Y6: =_xlfn.XLOOKUP('Sheet1 (4)'!AB12,'Sheet1 (3)'!B:B,'Sheet1 (3)'!D:D,"",0) -> プライム
A7: 6 | B7: =_xlfn.XLOOKUP('Sheet1 (4)'!AB13,'Sheet1 (3)'!B:B,'Sheet1 (3)'!C:C,"",0) -> ＡＤワークスグループ | C7: =_xlfn.XLOOKUP('Sheet1 (4)'!AB13,'Sheet1 (3)'!B:B,'Sheet1 (3)'!F:F,"",0) -> 不動産業 | D7: =ROUND('Sheet1 (4)'!E13/100000000,2) -> 0.49 | E7: =ROUND('Sheet1 (4)'!F13/100,2) -> 9.27 | F7: =ROUND('Sheet1 (4)'!G13/100,2) -> 13.7 | G7: =ROUND('Sheet1 (4)'!H13/100,2) -> 24.35 | H7: =ROUND('Sheet1 (4)'!I13/100,2) -> 32.09 | I7: =ROUND('Sheet1 (4)'!J13/100,2) -> 32.09 | J7: =ROUND('Sheet1 (4)'!K13/100,2) -> #VALUE! | K7: =ROUND('Sheet1 (4)'!L13/100,2) -> #VALUE! | L7: =ROUND(('Sheet1 (4)'!M13+'Sheet1 (4)'!R13)/100,2) -> -45.86 | M7: =ROUND(('Sheet1 (4)'!N13+'Sheet1 (4)'!S13)/100,2) -> -113.12 | N7: =ROUND(('Sheet1 (4)'!O13+'Sheet1 (4)'!T13)/100,2) -> -8.29 | O7: =ROUND(('Sheet1 (4)'!P13+'Sheet1 (4)'!U13)/100,2) -> 13.96 | P7: =ROUND(('Sheet1 (4)'!Q13+'Sheet1 (4)'!V13)/100,2) -> 13.96 | Q7: =ROUND('Sheet1 (4)'!W13/100,2) -> 0.02 | R7: =ROUND('Sheet1 (4)'!X13/100,2) -> 0.04 | S7: =ROUND('Sheet1 (4)'!Y13/100,2) -> 0.09 | T7: =ROUND('Sheet1 (4)'!Z13/100,2) -> 0.09 | U7: =ROUND('Sheet1 (4)'!AA13/100,2) -> 0.09 | V7: ='Sheet1 (4)'!AB13&".T" -> 2982.T | W7: =ROUND('Sheet1 (4)'!AC13,2) -> 9.92 | X7: =ROUND('Sheet1 (4)'!AD13,2) -> 1.15 | Y7: =_xlfn.XLOOKUP('Sheet1 (4)'!AB13,'Sheet1 (3)'!B:B,'Sheet1 (3)'!D:D,"",0) -> プライム
A8: 7 | B8: =_xlfn.XLOOKUP('Sheet1 (4)'!AB14,'Sheet1 (3)'!B:B,'Sheet1 (3)'!C:C,"",0) -> ＡＢ＆Ｃｏｍｐａｎｙ | C8: =_xlfn.XLOOKUP('Sheet1 (4)'!AB14,'Sheet1 (3)'!B:B,'Sheet1 (3)'!F:F,"",0) -> サービス業 | D8: =ROUND('Sheet1 (4)'!E14/100000000,2) -> 0.14 | E8: =ROUND('Sheet1 (4)'!F14/100,2) -> 15.26 | F8: =ROUND('Sheet1 (4)'!G14/100,2) -> 13.68 | G8: =ROUND('Sheet1 (4)'!H14/100,2) -> 18.52 | H8: =ROUND('Sheet1 (4)'!I14/100,2) -> 16.79 | I8: =ROUND('Sheet1 (4)'!J14/100,2) -> 16.79 | J8: =ROUND('Sheet1 (4)'!K14/100,2) -> 17.5 | K8: =ROUND('Sheet1 (4)'!L14/100,2) -> 18.5 | L8: =ROUND(('Sheet1 (4)'!M14+'Sheet1 (4)'!R14)/100,2) -> 17.72 | M8: =ROUND(('Sheet1 (4)'!N14+'Sheet1 (4)'!S14)/100,2) -> 15.85 | N8: =ROUND(('Sheet1 (4)'!O14+'Sheet1 (4)'!T14)/100,2) -> 20.77 | O8: =ROUND(('Sheet1 (4)'!P14+'Sheet1 (4)'!U14)/100,2) -> 27.11 | P8: =ROUND(('Sheet1 (4)'!Q14+'Sheet1 (4)'!V14)/100,2) -> 27.11 | Q8: =ROUND('Sheet1 (4)'!W14/100,2) -> 0.15 | R8: =ROUND('Sheet1 (4)'!X14/100,2) -> 0.11 | S8: =ROUND('Sheet1 (4)'!Y14/100,2) -> 0.13 | T8: =ROUND('Sheet1 (4)'!Z14/100,2) -> 0.13 | U8: =ROUND('Sheet1 (4)'!AA14/100,2) -> 0.13 | V8: ='Sheet1 (4)'!AB14&".T" -> 9251.T | W8: =ROUND('Sheet1 (4)'!AC14,2) -> 15.04 | X8: =ROUND('Sheet1 (4)'!AD14,2) -> 1.71 | Y8: =_xlfn.XLOOKUP('Sheet1 (4)'!AB14,'Sheet1 (3)'!B:B,'Sheet1 (3)'!D:D,"",0) -> グロース
A9: 8 | B9: =_xlfn.XLOOKUP('Sheet1 (4)'!AB15,'Sheet1 (3)'!B:B,'Sheet1 (3)'!C:C,"",0) -> Ａｂａｌａｎｃｅ | C9: =_xlfn.XLOOKUP('Sheet1 (4)'!AB15,'Sheet1 (3)'!B:B,'Sheet1 (3)'!F:F,"",0) -> 電気機器 | D9: =ROUND('Sheet1 (4)'!E15/100000000,2) -> 0.19 | E9: =ROUND('Sheet1 (4)'!F15/100,2) -> 13.62 | F9: =ROUND('Sheet1 (4)'!G15/100,2) -> 15.81 | G9: =ROUND('Sheet1 (4)'!H15/100,2) -> 128.05 | H9: =ROUND('Sheet1 (4)'!I15/100,2) -> 232.68 | I9: =ROUND('Sheet1 (4)'!J15/100,2) -> 48.17 | J9: =ROUND('Sheet1 (4)'!K15/100,2) -> #VALUE! | K9: =ROUND('Sheet1 (4)'!L15/100,2) -> #VALUE! | L9: =ROUND(('Sheet1 (4)'!M15+'Sheet1 (4)'!R15)/100,2) -> -19.99 | M9: =ROUND(('Sheet1 (4)'!N15+'Sheet1 (4)'!S15)/100,2) -> -196.7 | N9: =ROUND(('Sheet1 (4)'!O15+'Sheet1 (4)'!T15)/100,2) -> -21.44 | O9: =ROUND(('Sheet1 (4)'!P15+'Sheet1 (4)'!U15)/100,2) -> 235.66 | P9: =ROUND(('Sheet1 (4)'!Q15+'Sheet1 (4)'!V15)/100,2) -> -173.08 | Q9: =ROUND('Sheet1 (4)'!W15/100,2) -> 0.27 | R9: =ROUND('Sheet1 (4)'!X15/100,2) -> 0.24 | S9: =ROUND('Sheet1 (4)'!Y15/100,2) -> 0.78 | T9: =ROUND('Sheet1 (4)'!Z15/100,2) -> 0.62 | U9: =ROUND('Sheet1 (4)'!AA15/100,2) -> #VALUE! | V9: ='Sheet1 (4)'!AB15&".T" -> 3856.T | W9: =ROUND('Sheet1 (4)'!AC15,2) -> 14.1 | X9: =ROUND('Sheet1 (4)'!AD15,2) -> 0.73 | Y9: =_xlfn.XLOOKUP('Sheet1 (4)'!AB15,'Sheet1 (3)'!B:B,'Sheet1 (3)'!D:D,"",0) -> スタンダード
A10: 9 | B10: =_xlfn.XLOOKUP('Sheet1 (4)'!AB16,'Sheet1 (3)'!B:B,'Sheet1 (3)'!C:C,"",0) -> ａｂｃ | C10: =_xlfn.XLOOKUP('Sheet1 (4)'!AB16,'Sheet1 (3)'!B:B,'Sheet1 (3)'!F:F,"",0) -> その他金融業 | D10: =ROUND('Sheet1 (4)'!E16/100000000,2) -> 0.29 | E10: =ROUND('Sheet1 (4)'!F16/100,2) -> -14.65 | F10: =ROUND('Sheet1 (4)'!G16/100,2) -> -6.99 | G10: =ROUND('Sheet1 (4)'!H16/100,2) -> -19.14 | H10: =ROUND('Sheet1 (4)'!I16/100,2) -> -21.16 | I10: =ROUND('Sheet1 (4)'!J16/100,2) -> -26.15 | J10: =ROUND('Sheet1 (4)'!K16/100,2) -> #VALUE! | K10: =ROUND('Sheet1 (4)'!L16/100,2) -> #VALUE! | L10: =ROUND(('Sheet1 (4)'!M16+'Sheet1 (4)'!R16)/100,2) -> -1.64 | M10: =ROUND(('Sheet1 (4)'!N16+'Sheet1 (4)'!S16)/100,2) -> -12 | N10: =ROUND(('Sheet1 (4)'!O16+'Sheet1 (4)'!T16)/100,2) -> -42.09 | O10: =ROUND(('Sheet1 (4)'!P16+'Sheet1 (4)'!U16)/100,2) -> -20.97 | P10: =ROUND(('Sheet1 (4)'!Q16+'Sheet1 (4)'!V16)/100,2) -> -58.45 | Q10: =ROUND('Sheet1 (4)'!W16/100,2) -> -2.2 | R10: =ROUND('Sheet1 (4)'!X16/100,2) -> -4.5 | S10: =ROUND('Sheet1 (4)'!Y16/100,2) -> -2.56 | T10: =ROUND('Sheet1 (4)'!Z16/100,2) -> -3.29 | U10: =ROUND('Sheet1 (4)'!AA16/100,2) -> -2.93 | V10: ='Sheet1 (4)'!AB16&".T" -> 8783.T | W10: =ROUND('Sheet1 (4)'!AC16,2) -> #VALUE! | X10: =ROUND('Sheet1 (4)'!AD16,2) -> 2.2 | Y10: =_xlfn.XLOOKUP('Sheet1 (4)'!AB16,'Sheet1 (3)'!B:B,'Sheet1 (3)'!D:D,"",0) -> スタンダード
A11: 10 | B11: =_xlfn.XLOOKUP('Sheet1 (4)'!AB17,'Sheet1 (3)'!B:B,'Sheet1 (3)'!C:C,"",0) -> エービーシー・マート | C11: =_xlfn.XLOOKUP('Sheet1 (4)'!AB17,'Sheet1 (3)'!B:B,'Sheet1 (3)'!F:F,"",0) -> 小売業 | D11: =ROUND('Sheet1 (4)'!E17/100000000,2) -> 2.48 | E11: =ROUND('Sheet1 (4)'!F17/100,2) -> 195.15 | F11: =ROUND('Sheet1 (4)'!G17/100,2) -> 274.48 | G11: =ROUND('Sheet1 (4)'!H17/100,2) -> 423.02 | H11: =ROUND('Sheet1 (4)'!I17/100,2) -> 556.72 | I11: =ROUND('Sheet1 (4)'!J17/100,2) -> 625.51 | J11: =ROUND('Sheet1 (4)'!K17/100,2) -> 648.22 | K11: =ROUND('Sheet1 (4)'!L17/100,2) -> 674.87 | L11: =ROUND(('Sheet1 (4)'!M17+'Sheet1 (4)'!R17)/100,2) -> 121.71 | M11: =ROUND(('Sheet1 (4)'!N17+'Sheet1 (4)'!S17)/100,2) -> 176.99 | N11: =ROUND(('Sheet1 (4)'!O17+'Sheet1 (4)'!T17)/100,2) -> 18.79 | O11: =ROUND(('Sheet1 (4)'!P17+'Sheet1 (4)'!U17)/100,2) -> 398.25 | P11: =ROUND(('Sheet1 (4)'!Q17+'Sheet1 (4)'!V17)/100,2) -> 410.22 | Q11: =ROUND('Sheet1 (4)'!W17/100,2) -> 0.07 | R11: =ROUND('Sheet1 (4)'!X17/100,2) -> 0.06 | S11: =ROUND('Sheet1 (4)'!Y17/100,2) -> 0.1 | T11: =ROUND('Sheet1 (4)'!Z17/100,2) -> 0.12 | U11: =ROUND('Sheet1 (4)'!AA17/100,2) -> 0.13 | V11: ='Sheet1 (4)'!AB17&".T" -> 2670.T | W11: =ROUND('Sheet1 (4)'!AC17,2) -> 14.52 | X11: =ROUND('Sheet1 (4)'!AD17,2) -> 1.74 | Y11: =_xlfn.XLOOKUP('Sheet1 (4)'!AB17,'Sheet1 (3)'!B:B,'Sheet1 (3)'!D:D,"",0) -> プライム
A12: 11 | B12: =_xlfn.XLOOKUP('Sheet1 (4)'!AB18,'Sheet1 (3)'!B:B,'Sheet1 (3)'!C:C,"",0) -> ＡＢＥＪＡ | C12: =_xlfn.XLOOKUP('Sheet1 (4)'!AB18,'Sheet1 (3)'!B:B,'Sheet1 (3)'!F:F,"",0) -> 情報・通信業 | D12: =ROUND('Sheet1 (4)'!E18/100000000,2) -> 0.09 | E12: =ROUND('Sheet1 (4)'!F18/100,2) -> -2.65 | F12: =ROUND('Sheet1 (4)'!G18/100,2) -> -1.63 | G12: =ROUND('Sheet1 (4)'!H18/100,2) -> 4.03 | H12: =ROUND('Sheet1 (4)'!I18/100,2) -> 2.91 | I12: =ROUND('Sheet1 (4)'!J18/100,2) -> 4.46 | J12: =ROUND('Sheet1 (4)'!K18/100,2) -> 4.8 | K12: =ROUND('Sheet1 (4)'!L18/100,2) -> 5.99 | L12: =ROUND(('Sheet1 (4)'!M18+'Sheet1 (4)'!R18)/100,2) -> #VALUE! | M12: =ROUND(('Sheet1 (4)'!N18+'Sheet1 (4)'!S18)/100,2) -> #VALUE! | N12: =ROUND(('Sheet1 (4)'!O18+'Sheet1 (4)'!T18)/100,2) -> 4.55 | O12: =ROUND(('Sheet1 (4)'!P18+'Sheet1 (4)'!U18)/100,2) -> -7.88 | P12: =ROUND(('Sheet1 (4)'!Q18+'Sheet1 (4)'!V18)/100,2) -> 15.93 | Q12: =ROUND('Sheet1 (4)'!W18/100,2) -> #VALUE! | R12: =ROUND('Sheet1 (4)'!X18/100,2) -> -0.1 | S12: =ROUND('Sheet1 (4)'!Y18/100,2) -> 0.16 | T12: =ROUND('Sheet1 (4)'!Z18/100,2) -> 0.06 | U12: =ROUND('Sheet1 (4)'!AA18/100,2) -> 0.11 | V12: ='Sheet1 (4)'!AB18&".T" -> 5574.T | W12: =ROUND('Sheet1 (4)'!AC18,2) -> 63.36 | X12: =ROUND('Sheet1 (4)'!AD18,2) -> 5.97 | Y12: =_xlfn.XLOOKUP('Sheet1 (4)'!AB18,'Sheet1 (3)'!B:B,'Sheet1 (3)'!D:D,"",0) -> グロース
A13: 12 | B13: =_xlfn.XLOOKUP('Sheet1 (4)'!AB19,'Sheet1 (3)'!B:B,'Sheet1 (3)'!C:C,"",0) -> ＡＢホテル | C13: =_xlfn.XLOOKUP('Sheet1 (4)'!AB19,'Sheet1 (3)'!B:B,'Sheet1 (3)'!F:F,"",0) -> サービス業 | D13: =ROUND('Sheet1 (4)'!E19/100000000,2) -> 0.14 | E13: =ROUND('Sheet1 (4)'!F19/100,2) -> 0.45 | F13: =ROUND('Sheet1 (4)'!G19/100,2) -> 9.59 | G13: =ROUND('Sheet1 (4)'!H19/100,2) -> 29.77 | H13: =ROUND('Sheet1 (4)'!I19/100,2) -> 36.12 | I13: =ROUND('Sheet1 (4)'!J19/100,2) -> 39.63 | J13: =ROUND('Sheet1 (4)'!K19/100,2) -> #VALUE! | K13: =ROUND('Sheet1 (4)'!L19/100,2) -> #VALUE! | L13: =ROUND(('Sheet1 (4)'!M19+'Sheet1 (4)'!R19)/100,2) -> -20.75 | M13: =ROUND(('Sheet1 (4)'!N19+'Sheet1 (4)'!S19)/100,2) -> 15.4 | N13: =ROUND(('Sheet1 (4)'!O19+'Sheet1 (4)'!T19)/100,2) -> 28.02 | O13: =ROUND(('Sheet1 (4)'!P19+'Sheet1 (4)'!U19)/100,2) -> 16.81 | P13: =ROUND(('Sheet1 (4)'!Q19+'Sheet1 (4)'!V19)/100,2) -> -5.01 | Q13: =ROUND('Sheet1 (4)'!W19/100,2) -> 0 | R13: =ROUND('Sheet1 (4)'!X19/100,2) -> 0.09 | S13: =ROUND('Sheet1 (4)'!Y19/100,2) -> 0.24 | T13: =ROUND('Sheet1 (4)'!Z19/100,2) -> 0.25 | U13: =ROUND('Sheet1 (4)'!AA19/100,2) -> 0.22 | V13: ='Sheet1 (4)'!AB19&".T" -> 6565.T | W13: =ROUND('Sheet1 (4)'!AC19,2) -> 8.54 | X13: =ROUND('Sheet1 (4)'!AD19,2) -> 1.74 | Y13: =_xlfn.XLOOKUP('Sheet1 (4)'!AB19,'Sheet1 (3)'!B:B,'Sheet1 (3)'!D:D,"",0) -> スタンダード
... A4226: 4225 | B4226: =_xlfn.XLOOKUP('Sheet1 (4)'!AB4232,'Sheet1 (3)'!B:B,'Sheet1 (3)'!C:C,"",0) -> 0 | C4226: =_xlfn.XLOOKUP('Sheet1 (4)'!AB4232,'Sheet1 (3)'!B:B,'Sheet1 (3)'!F:F,"",0) -> 0 | D4226: =ROUND('Sheet1 (4)'!E4232/100000000,2) -> 0 | E4226: =ROUND('Sheet1 (4)'!F4232/100,2) -> 0 | F4226: =ROUND('Sheet1 (4)'!G4232/100,2) -> 0 | G4226: =ROUND('Sheet1 (4)'!H4232/100,2) -> 0 | H4226: =ROUND('Sheet1 (4)'!I4232/100,2) -> 0 | I4226: =ROUND('Sheet1 (4)'!J4232/100,2) -> 0 | J4226: =ROUND('Sheet1 (4)'!K4232/100,2) -> 0 | K4226: =ROUND('Sheet1 (4)'!L4232/100,2) -> 0 | L4226: =ROUND(('Sheet1 (4)'!M4232+'Sheet1 (4)'!R4232)/100,2) -> 0 | M4226: =ROUND(('Sheet1 (4)'!N4232+'Sheet1 (4)'!S4232)/100,2) -> 0 | N4226: =ROUND(('Sheet1 (4)'!O4232+'Sheet1 (4)'!T4232)/100,2) -> 0 | O4226: =ROUND(('Sheet1 (4)'!P4232+'Sheet1 (4)'!U4232)/100,2) -> 0 | P4226: =ROUND(('Sheet1 (4)'!Q4232+'Sheet1 (4)'!V4232)/100,2) -> 0 | Q4226: =ROUND('Sheet1 (4)'!W4232/100,2) -> 0 | R4226: =ROUND('Sheet1 (4)'!X4232/100,2) -> 0 | S4226: =ROUND('Sheet1 (4)'!Y4232/100,2) -> 0 | T4226: =ROUND('Sheet1 (4)'!Z4232/100,2) -> 0 | U4226: =ROUND('Sheet1 (4)'!AA4232/100,2) -> 0 | V4226: ='Sheet1 (4)'!AB4232&".T" -> .T | W4226: =ROUND('Sheet1 (4)'!AC4232,2) -> 0 | X4226: =ROUND('Sheet1 (4)'!AD4232,2) -> 0 | Y4226: =_xlfn.XLOOKUP('Sheet1 (4)'!AB4232,'Sheet1 (3)'!B:B,'Sheet1 (3)'!D:D,"",0) -> 0

Sheet Sheet1 (3)
A1: 日付 | B1: コード | C1: 銘柄名 | D1: 市場・商品区分 | E1: 33業種コード | F1: 33業種区分 | G1: 17業種コード | H1: 17業種区分 | I1: 規模コード | J1: 規模区分
A2: 20251031 | B2: 1301 | C2: 極洋 | D2: プライム | E2: 50 | F2: 水産・農林業 | G2: 1 | H2: 食品 | I2: 6 | J2: TOPIX Small 1
A3: 20251031 | B3: 1305 | C3: ｉＦｒｅｅＥＴＦ ＴＯＰＩＸ（年１回決算型） | D3: ETF・ETN | E3: - | F3: - | G3: - | H3: - | I3: - | J3: -
A4: 20251031 | B4: 1306 | C4: ＮＥＸＴ ＦＵＮＤＳ ＴＯＰＩＸ連動型上場投信 | D4: ETF・ETN | E4: - | F4: - | G4: - | H4: - | I4: - | J4: -
A5: 20251031 | B5: 1308 | C5: 上場インデックスファンドＴＯＰＩＸ | D5: ETF・ETN | E5: - | F5: - | G5: - | H5: - | I5: - | J5: -
A6: 20251031 | B6: 1309 | C6: ＮＥＸＴ ＦＵＮＤＳ ＣｈｉｎａＡＭＣ・中国株式・上証５０連動型上場投信 | D6: ETF・ETN | E6: - | F6: - | G6: - | H6: - | I6: - | J6: -
A7: 20251031 | B7: 130A | C7: Ｖｅｒｉｔａｓ Ｉｎ Ｓｉｌｉｃｏ | D7: グロース | E7: 3250 | F7: 医薬品 | G7: 5 | H7: 医薬品 | I7: - | J7: -
A8: 20251031 | B8: 1311 | C8: ＮＥＸＴ ＦＵＮＤＳ ＴＯＰＩＸ Ｃｏｒｅ ３０連動型上場投信 | D8: ETF・ETN | E8: - | F8: - | G8: - | H8: - | I8: - | J8: -
A9: 20251031 | B9: 1319 | C9: ＮＥＸＴ ＦＵＮＤＳ 日経３００株価指数連動型上場投信 | D9: ETF・ETN | E9: - | F9: - | G9: - | H9: - | I9: - | J9: -
A10: 20251031 | B10: 131A | C10: ＣＣＮグループ | D10: PRO Market | E10: 5250 | F10: 情報・通信業 | G10: 10 | H10: 情報通信・サービスその他 | I10: - | J10: -
A11: 20251031 | B11: 1320 | C11: ｉＦｒｅｅＥＴＦ 日経２２５（年１回決算型） | D11: ETF・ETN | E11: - | F11: - | G11: - | H11: - | I11: - | J11: -
A12: 20251031 | B12: 1321 | C12: ＮＥＸＴ ＦＵＮＤＳ 日経２２５連動型上場投信 | D12: ETF・ETN | E12: - | F12: - | G12: - | H12: - | I12: - | J12: -
A13: 20251031 | B13: 1322 | C13: 上場インデックスファンド中国Ａ株（パンダ）Ｅ Ｆｕｎｄ ＣＳＩ３００ | D13: ETF・ETN | E13: - | F13: - | G13: - | H13: - | I13: - | J13: -
A14: 20251031 | B14: 1325 | C14: ＮＥＸＴ ＦＵＮＤＳ ブラジル株式指数・ボベスパ連動型上場投信 | D14: ETF・ETN | E14: - | F14: - | G14: - | H14: - | I14: - | J14: -
A15: 20251031 | B15: 1326 | C15: ＳＰＤＲゴールド・シェア | D15: ETF・ETN | E15: - | F15: - | G15: - | H15: - | I15: - | J15: -
A16: 20251031 | B16: 1328 | C16: ＮＥＸＴ ＦＵＮＤＳ 金価格連動型上場投信 | D16: ETF・ETN | E16: - | F16: - | G16: - | H16: - | I16: - | J16: -
A17: 20251031 | B17: 1329 | C17: ｉシェアーズ・コア 日経２２５ ＥＴＦ | D17: ETF・ETN | E17: - | F17: - | G17: - | H17: - | I17: - | J17: -
A18: 20251031 | B18: 132A | C18: アイエヌホールディングス | D18: PRO Market | E18: 5050 | F18: 陸運業 | G18: 12 | H18: 運輸・物流 | I18: - | J18: -
A19: 20251031 | B19: 1330 | C19: 上場インデックスファンド２２５ | D19: ETF・ETN | E19: - | F19: - | G19: - | H19: - | I19: - | J19: -
A20: 20251031 | B20: 1332 | C20: ニッスイ | D20: プライム | E20: 50 | F20: 水産・農林業 | G20: 1 | H20: 食品 | I20: 4 | J20: TOPIX Mid400
A21: 20251031 | B21: 1333 | C21: マルハニチロ | D21: プライム | E21: 50 | F21: 水産・農林業 | G21: 1 | H21: 食品 | I21: 4 | J21: TOPIX Mid400
A22: 20251031 | B22: 133A | C22: グローバルＸ 超短期米国債 ＥＴＦ | D22: ETF・ETN | E22: - | F22: - | G22: - | H22: - | I22: - | J22: -
A23: 20251031 | B23: 1343 | C23: ＮＥＸＴ ＦＵＮＤＳ 東証ＲＥＩＴ 指数連動型上場投信 | D23: ETF・ETN | E23: - | F23: - | G23: - | H23: - | I23: - | J23: -
A24: 20251031 | B24: 1345 | C24: 上場インデックスファンドＪリート（東証ＲＥＩＴ指数）隔月分配型 | D24: ETF・ETN | E24: - | F24: - | G24: - | H24: - | I24: - | J24: -
A25: 20251031 | B25: 1346 | C25: ＭＡＸＩＳ 日経２２５上場投信 | D25: ETF・ETN | E25: - | F25: - | G25: - | H25: - | I25: - | J25: -
A26: 20251031 | B26: 1348 | C26: ＭＡＸＩＳ トピックス上場投信 | D26: ETF・ETN | E26: - | F26: - | G26: - | H26: - | I26: - | J26: -
A27: 20251031 | B27: 1349 | C27: ＡＢＦ汎アジア債券インデックス・ファンド | D27: ETF・ETN | E27: - | F27: - | G27: - | H27: - | I27: - | J27: -
A28: 20251031 | B28: 134A | C28: アプライズ | D28: PRO Market | E28: 9050 | F28: サービス業 | G28: 10 | H28: 情報通信・サービスその他 | I28: - | J28: -
A29: 20251031 | B29: 1356 | C29: ＴＯＰＩＸベア２倍上場投信 | D29: ETF・ETN | E29: - | F29: - | G29: - | H29: - | I29: - | J29: -
A30: 20251031 | B30: 1357 | C30: ＮＥＸＴ ＦＵＮＤＳ 日経平均ダブルインバース・インデックス連動型上場投信 | D30: ETF・ETN | E30: - | F30: - | G30: - | H30: - | I30: - | J30: -
A31: 20251031 | B31: 1358 | C31: 上場インデックスファンド日経レバレッジ指数 | D31: ETF・ETN | E31: - | F31: - | G31: - | H31: - | I31: - | J31: -
A32: 20251031 | B32: 135A | C32: ＶＲＡＩＮ Ｓｏｌｕｔｉｏｎ | D32: グロース | E32: 5250 | F32: 情報・通信業 | G32: 10 | H32: 情報通信・サービスその他 | I32: - | J32: -
A33: 20251031 | B33: 1360 | C33: 日経平均ベア２倍上場投信 | D33: ETF・ETN | E33: - | F33: - | G33: - | H33: - | I33: - | J33: -
A34: 20251031 | B34: 1364 | C34: ｉシェアーズ ＪＰＸ日経４００ ＥＴＦ | D34: ETF・ETN | E34: - | F34: - | G34: - | H34: - | I34: - | J34: -
A35: 20251031 | B35: 1365 | C35: ｉＦｒｅｅＥＴＦ 日経平均レバレッジ・インデックス | D35: ETF・ETN | E35: - | F35: - | G35: - | H35: - | I35: - | J35: -
A36: 20251031 | B36: 1366 | C36: ｉＦｒｅｅＥＴＦ 日経平均ダブルインバース・インデックス | D36: ETF・ETN | E36: - | F36: - | G36: - | H36: - | I36: - | J36: -
A37: 20251031 | B37: 1367 | C37: ｉＦｒｅｅＥＴＦ ＴＯＰＩＸレバレッジ（２倍）指数 | D37: ETF・ETN | E37: - | F37: - | G37: - | H37: - | I37: - | J37: -
A38: 20251031 | B38: 1368 | C38: ｉＦｒｅｅＥＴＦ ＴＯＰＩＸダブルインバース（－２倍）指数 | D38: ETF・ETN | E38: - | F38: - | G38: - | H38: - | I38: - | J38: -
A39: 20251031 | B39: 1369 | C39: Ｏｎｅ ＥＴＦ 日経２２５ | D39: ETF・ETN | E39: - | F39: - | G39: - | H39: - | I39: - | J39: -
A40: 20251031 | B40: 136A | C40: 三興商事 | D40: PRO Market | E40: 2050 | F40: 建設業 | G40: 3 | H40: 建設・資材 | I40: - | J40: -
A41: 20251031 | B41: 1375 | C41: ユキグニファクトリー | D41: プライム | E41: 50 | F41: 水産・農林業 | G41: 1 | H41: 食品 | I41: 7 | J41: TOPIX Small 2
A42: 20251031 | B42: 1376 | C42: カネコ種苗 | D42: スタンダード | E42: 50 | F42: 水産・農林業 | G42: 1 | H42: 食品 | I42: 7 | J42: TOPIX Small 2
A43: 20251031 | B43: 1377 | C43: サカタのタネ | D43: プライム | E43: 50 | F43: 水産・農林業 | G43: 1 | H43: 食品 | I43: 6 | J43: TOPIX Small 1
A44: 20251031 | B44: 1379 | C44: ホクト | D44: プライム | E44: 50 | F44: 水産・農林業 | G44: 1 | H44: 食品 | I44: 7 | J44: TOPIX Small 2
A45: 20251031 | B45: 137A | C45: Ｃｏｃｏｌｉｖｅ | D45: グロース | E45: 5250 | F45: 情報・通信業 | G45: 10 | H45: 情報通信・サービスその他 | I45: - | J45: -
A46: 20251031 | B46: 1380 | C46: 秋川牧園 | D46: スタンダード | E46: 50 | F46: 水産・農林業 | G46: 1 | H46: 食品 | I46: - | J46: -
A47: 20251031 | B47: 1381 | C47: アクシーズ | D47: スタンダード | E47: 50 | F47: 水産・農林業 | G47: 1 | H47: 食品 | I47: - | J47: -
A48: 20251031 | B48: 1382 | C48: ホーブ | D48: スタンダード | E48: 50 | F48: 水産・農林業 | G48: 1 | H48: 食品 | I48: - | J48: -
A49: 20251031 | B49: 1383 | C49: ベルグアース | D49: スタンダード | E49: 50 | F49: 水産・農林業 | G49: 1 | H49: 食品 | I49: - | J49: -
A50: 20251031 | B50: 1384 | C50: ホクリヨウ | D50: スタンダード | E50: 50 | F50: 水産・農林業 | G50: 1 | H50: 食品 | I50: - | J50: -
A51: 20251031 | B51: 138A | C51: 光フードサービス | D51: グロース | E51: 6100 | F51: 小売業 | G51: 14 | H51: 小売 | I51: - | J51: -
A52: 20251031 | B52: 1397 | C52: ＳＭＤＡＭ 日経２２５上場投信 | D52: ETF・ETN | E52: - | F52: - | G52: - | H52: - | I52: - | J52: -
A53: 20251031 | B53: 1398 | C53: ＳＭＤＡＭ 東証ＲＥＩＴ指数上場投信 | D53: ETF・ETN | E53: - | F53: - | G53: - | H53: - | I53: - | J53: -
A54: 20251031 | B54: 1399 | C54: 上場インデックスファンドＭＳＣＩ日本株高配当低ボラティリティ | D54: ETF・ETN | E54: - | F54: - | G54: - | H54: - | I54: - | J54: -
A55: 20251031 | B55: 139A | C55: 東日本地所 | D55: PRO Market | E55: 8050 | F55: 不動産業 | G55: 17 | H55: 不動産 | I55: - | J55: -
A56: 20251031 | B56: 1401 | C56: エムビーエス | D56: グロース | E56: 2050 | F56: 建設業 | G56: 3 | H56: 建設・資材 | I56: - | J56: -
A57: 20251031 | B57: 1407 | C57: ウエストホールディングス | D57: スタンダード | E57: 2050 | F57: 建設業 | G57: 3 | H57: 建設・資材 | I57: - | J57: -
A58: 20251031 | B58: 140A | C58: ｉＦｒｅｅＥＴＦ 米国１０年国債先物インバース | D58: ETF・ETN | E58: - | F58: - | G58: - | H58: - | I58: - | J58: -
A59: 20251031 | B59: 1414 | C59: ショーボンドホールディングス | D59: プライム | E59: 2050 | F59: 建設業 | G59: 3 | H59: 建設・資材 | I59: 4 | J59: TOPIX Mid400
A60: 20251031 | B60: 1417 | C60: ミライト・ワン | D60: プライム | E60: 2050 | F60: 建設業 | G60: 3 | H60: 建設・資材 | I60: 4 | J60: TOPIX Mid400
A61: 20251031 | B61: 1418 | C61: インターライフホールディングス | D61: スタンダード | E61: 2050 | F61: 建設業 | G61: 3 | H61: 建設・資材 | I61: - | J61: -
A62: 20251031 | B62: 1419 | C62: タマホーム | D62: プライム | E62: 2050 | F62: 建設業 | G62: 3 | H62: 建設・資材 | I62: 6 | J62: TOPIX Small 1
A63: 20251031 | B63: 141A | C63: トライアルホールディングス | D63: グロース | E63: 6100 | F63: 小売業 | G63: 14 | H63: 小売 | I63: - | J63: -
A64: 20251031 | B64: 1420 | C64: サンヨーホームズ | D64: スタンダード | E64: 2050 | F64: 建設業 | G64: 3 | H64: 建設・資材 | I64: - | J64: -
A65: 20251031 | B65: 1429 | C65: 日本アクア | D65: プライム | E65: 2050 | F65: 建設業 | G65: 3 | H65: 建設・資材 | I65: - | J65: -
A66: 20251031 | B66: 142A | C66: ジンジブ | D66: グロース | E66: 9050 | F66: サービス業 | G66: 10 | H66: 情報通信・サービスその他 | I66: - | J66: -
A67: 20251031 | B67: 1430 | C67: ファーストコーポレーション | D67: スタンダード | E67: 2050 | F67: 建設業 | G67: 3 | H67: 建設・資材 | I67: - | J67: -
A68: 20251031 | B68: 1431 | C68: Ｌｉｂ Ｗｏｒｋ | D68: グロース | E68: 2050 | F68: 建設業 | G68: 3 | H68: 建設・資材 | I68: - | J68: -
A69: 20251031 | B69: 1432 | C69: 動力 | D69: PRO Market | E69: 2050 | F69: 建設業 | G69: 3 | H69: 建設・資材 | I69: - | J69: -
A70: 20251031 | B70: 1433 | C70: ベステラ | D70: プライム | E70: 2050 | F70: 建設業 | G70: 3 | H70: 建設・資材 | I70: - | J70: -
A71: 20251031 | B71: 1434 | C71: ＪＥＳＣＯホールディングス | D71: スタンダード | E71: 2050 | F71: 建設業 | G71: 3 | H71: 建設・資材 | I71: - | J71: -
A72: 20251031 | B72: 1435 | C72: ｒｏｂｏｔ ｈｏｍｅ | D72: スタンダード | E72: 8050 | F72: 不動産業 | G72: 17 | H72: 不動産 | I72: 7 | J72: TOPIX Small 2
A73: 20251031 | B73: 1436 | C73: グリーンエナジー＆カンパニー | D73: グロース | E73: 2050 | F73: 建設業 | G73: 3 | H73: 建設・資材 | I73: - | J73: -
A74: 20251031 | B74: 1438 | C74: 岐阜造園 | D74: スタンダード | E74: 2050 | F74: 建設業 | G74: 3 | H74: 建設・資材 | I74: - | J74: -
A75: 20251031 | B75: 143A | C75: イシン | D75: グロース | E75: 9050 | F75: サービス業 | G75: 10 | H75: 情報通信・サービスその他 | I75: - | J75: -
A76: 20251031 | B76: 1443 | C76: 技研ホールディングス | D76: スタンダード | E76: 2050 | F76: 建設業 | G76: 3 | H76: 建設・資材 | I76: - | J76: -
A77: 20251031 | B77: 1444 | C77: ニッソウ | D77: グロース | E77: 2050 | F77: 建設業 | G77: 3 | H77: 建設・資材 | I77: - | J77: -
A78: 20251031 | B78: 1445 | C78: ひかりホールディングス | D78: PRO Market | E78: 2050 | F78: 建設業 | G78: 3 | H78: 建設・資材 | I78: - | J78: -
A79: 20251031 | B79: 1446 | C79: キャンディル | D79: スタンダード | E79: 2050 | F79: 建設業 | G79: 3 | H79: 建設・資材 | I79: - | J79: -
A80: 20251031 | B80: 1447 | C80: ＳＡＡＦホールディングス | D80: グロース | E80: 2050 | F80: 建設業 | G80: 3 | H80: 建設・資材 | I80: - | J80: -
A81: 20251031 | B81: 144A | C81: エネルギーパワー | D81: PRO Market | E81: 2050 | F81: 建設業 | G81: 3 | H81: 建設・資材 | I81: - | J81: -
A82: 20251031 | B82: 1450 | C82: ＴＡＮＡＫＥＮ | D82: スタンダード | E82: 2050 | F82: 建設業 | G82: 3 | H82: 建設・資材 | I82: - | J82: -
A83: 20251031 | B83: 1452 | C83: 横浜ライト工業 | D83: PRO Market | E83: 2050 | F83: 建設業 | G83: 3 | H83: 建設・資材 | I83: - | J83: -
A84: 20251031 | B84: 1456 | C84: ｉＦｒｅｅＥＴＦ 日経平均インバース・インデックス | D84: ETF・ETN | E84: - | F84: - | G84: - | H84: - | I84: - | J84: -
A85: 20251031 | B85: 1457 | C85: ｉＦｒｅｅＥＴＦ ＴＯＰＩＸインバース（－１倍）指数 | D85: ETF・ETN | E85: - | F85: - | G85: - | H85: - | I85: - | J85: -
A86: 20251031 | B86: 1458 | C86: 楽天ＥＴＦ‐日経レバレッジ指数連動型 | D86: ETF・ETN | E86: - | F86: - | G86: - | H86: - | I86: - | J86: -
A87: 20251031 | B87: 1459 | C87: 楽天ＥＴＦ‐日経ダブルインバース指数連動型 | D87: ETF・ETN | E87: - | F87: - | G87: - | H87: - | I87: - | J87: -
A88: 20251031 | B88: 145A | C88: Ｌ ｉｓ Ｂ | D88: グロース | E88: 5250 | F88: 情報・通信業 | G88: 10 | H88: 情報通信・サービスその他 | I88: - | J88: -
A89: 20251031 | B89: 1466 | C89: ｉＦｒｅｅＥＴＦ ＪＰＸ日経４００ダブルインバース・インデックス | D89: ETF・ETN | E89: - | F89: - | G89: - | H89: - | I89: - | J89: -
A90: 20251031 | B90: 1469 | C90: ＪＰＸ日経４００ベア２倍上場投信（ダブルインバース） | D90: ETF・ETN | E90: - | F90: - | G90: - | H90: - | I90: - | J90: -
A91: 20251031 | B91: 146A | C91: コロンビア・ワークス | D91: スタンダード | E91: 8050 | F91: 不動産業 | G91: 17 | H91: 不動産 | I91: - | J91: -
A92: 20251031 | B92: 1472 | C92: ＮＥＸＴ ＦＵＮＤＳ ＪＰＸ日経４００ダブルインバース・インデックス連動型上場投信 | D92: ETF・ETN | E92: - | F92: - | G92: - | H92: - | I92: - | J92: -
A93: 20251031 | B93: 1473 | C93: Ｏｎｅ ＥＴＦ トピックス | D93: ETF・ETN | E93: - | F93: - | G93: - | H93: - | I93: - | J93: -
A94: 20251031 | B94: 1474 | C94: Ｏｎｅ ＥＴＦ ＪＰＸ日経４００ | D94: ETF・ETN | E94: - | F94: - | G94: - | H94: - | I94: - | J94: -
A95: 20251031 | B95: 1475 | C95: ｉシェアーズ・コア ＴＯＰＩＸ ＥＴＦ | D95: ETF・ETN | E95: - | F95: - | G95: - | H95: - | I95: - | J95: -
A96: 20251031 | B96: 1476 | C96: ｉシェアーズ・コア Ｊリート ＥＴＦ | D96: ETF・ETN | E96: - | F96: - | G96: - | H96: - | I96: - | J96: -
A97: 20251031 | B97: 1477 | C97: ｉシェアーズ ＭＳＣＩ 日本株最小分散 ＥＴＦ | D97: ETF・ETN | E97: - | F97: - | G97: - | H97: - | I97: - | J97: -
A98: 20251031 | B98: 1478 | C98: ｉシェアーズ ＭＳＣＩ ジャパン高配当利回り ＥＴＦ | D98: ETF・ETN | E98: - | F98: - | G98: - | H98: - | I98: - | J98: -
A99: 20251031 | B99: 1479 | C99: ｉＦｒｅｅＥＴＦ ＭＳＣＩ日本株人材設備投資指数 | D99: ETF・ETN | E99: - | F99: - | G99: - | H99: - | I99: - | J99: -
A100: 20251031 | B100: 147A | C100: ソラコム | D100: グロース | E100: 5250 | F100: 情報・通信業 | G100: 10 | H100: 情報通信・サービスその他 | I100: - | J100: -
...

Sheet Sheet1 (4)
A3: =SPGTable($B$8:$B$3910,$C$5:$AF$5,$C$6:$AF$6,"Options:Curr=JPY,Mag=Standard,ConvMethod=R,FilingVer=Current/Restated") -> #NAME?
A4: =SPGLabel(266637,267969,"","Options:Curr=JPY,Mag=Standard,ConvMethod=R,FilingVer=Current/Restated") -> #NAME? | B4: =SPGLabel(266637,267961,"","Options:Curr=JPY,Mag=Standard,ConvMethod=R,FilingVer=Current/Restated") -> #NAME? | C4: =SPGLabel(266637,313763,"","Options:Curr=JPY,Mag=Standard,ConvMethod=R,FilingVer=Current/Restated") -> #NAME? | D4: =SPGLabel(266637,268194,"","Options:Curr=JPY,Mag=Standard,ConvMethod=R,FilingVer=Current/Restated") -> #NAME? | E4: =SPGLabel(266637,329044,"11/06/2025","Options:Curr=JPY,Mag=Standard,ConvMethod=R,FilingVer=Current/Restated") -> #NAME? | F4: =SPGLabel(266637,329291,"FY2021","Options:Curr=JPY,Mag=Standard,ConvMethod=R,FilingVer=Current/Restated") -> #NAME? | G4: =SPGLabel(266637,329291,"FY2022","Options:Curr=JPY,Mag=Standard,ConvMethod=R,FilingVer=Current/Restated") -> #NAME? | H4: =SPGLabel(266637,329291,"FY2023","Options:Curr=JPY,Mag=Standard,ConvMethod=R,FilingVer=Current/Restated") -> #NAME? | I4: =SPGLabel(266637,329291,"FY2024","Options:Curr=JPY,Mag=Standard,ConvMethod=R,FilingVer=Current/Restated") -> #NAME? | J4: =SPGLabel(266637,329291,"FY0","Options:Curr=JPY,Mag=Standard,ConvMethod=R,FilingVer=Current/Restated") -> #NAME? | K4: =SPGLabel(266637,290546,"FY+1","Options:Curr=JPY,Mag=Standard,ConvMethod=R,FilingVer=Current/Restated") -> #NAME? | L4: =SPGLabel(266637,290546,"FY+2","Options:Curr=JPY,Mag=Standard,ConvMethod=R,FilingVer=Current/Restated") -> #NAME? | M4: =SPGLabel(266637,272591,"FY2021","Options:Curr=JPY,Mag=Standard,ConvMethod=R,FilingVer=Current/Restated") -> #NAME? | N4: =SPGLabel(266637,272591,"FY2022","Options:Curr=JPY,Mag=Standard,ConvMethod=R,FilingVer=Current/Restated") -> #NAME? | O4: =SPGLabel(266637,272591,"FY2023","Options:Curr=JPY,Mag=Standard,ConvMethod=R,FilingVer=Current/Restated") -> #NAME? | P4: =SPGLabel(266637,272591,"FY2024","Options:Curr=JPY,Mag=Standard,ConvMethod=R,FilingVer=Current/Restated") -> #NAME? | Q4: =SPGLabel(266637,272591,"FY0","Options:Curr=JPY,Mag=Standard,ConvMethod=R,FilingVer=Current/Restated") -> #NAME? | R4: =SPGLabel(266637,272601,"FY2021","Options:Curr=JPY,Mag=Standard,ConvMethod=R,FilingVer=Current/Restated") -> #NAME? | S4: =SPGLabel(266637,272601,"FY2022","Options:Curr=JPY,Mag=Standard,ConvMethod=R,FilingVer=Current/Restated") -> #NAME? | T4: =SPGLabel(266637,272601,"FY2023","Options:Curr=JPY,Mag=Standard,ConvMethod=R,FilingVer=Current/Restated") -> #NAME? | U4: =SPGLabel(266637,272601,"FY2024","Options:Curr=JPY,Mag=Standard,ConvMethod=R,FilingVer=Current/Restated") -> #NAME? | V4: =SPGLabel(266637,272601,"FY0","Options:Curr=JPY,Mag=Standard,ConvMethod=R,FilingVer=Current/Restated") -> #NAME? | W4: =SPGLabel(266637,329316,"FY2021","Options:Curr=JPY,Mag=Standard,ConvMethod=R,FilingVer=Current/Restated") -> #NAME? | X4: =SPGLabel(266637,329316,"FY2022","Options:Curr=JPY,Mag=Standard,ConvMethod=R,FilingVer=Current/Restated") -> #NAME? | Y4: =SPGLabel(266637,329316,"FY2023","Options:Curr=JPY,Mag=Standard,ConvMethod=R,FilingVer=Current/Restated") -> #NAME? | Z4: =SPGLabel(266637,329316,"FY2024","Options:Curr=JPY,Mag=Standard,ConvMethod=R,FilingVer=Current/Restated") -> #NAME? | AA4: =SPGLabel(266637,329316,"FY0","Options:Curr=JPY,Mag=Standard,ConvMethod=R,FilingVer=Current/Restated") -> #NAME? | AB4: =SPGLabel(266637,271442,"","Options:Curr=JPY,Mag=Standard,ConvMethod=R,FilingVer=Current/Restated") -> #NAME? | AC4: =SPGLabel(266637,371494,"LTM","Options:Curr=JPY,Mag=Standard,ConvMethod=R,FilingVer=Current/Restated") -> #NAME? | AD4: =SPGLabel(266637,371493,"LTM","Options:Curr=JPY,Mag=Standard,ConvMethod=R,FilingVer=Current/Restated") -> #NAME? | AE4: =SPGLabel(266637,271669,"","Options:Curr=JPY,Mag=Standard,ConvMethod=R,FilingVer=Current/Restated") -> #NAME? | AF4: =SPGLabel(266637,329068,"","Options:Curr=JPY,Mag=Standard,ConvMethod=R,FilingVer=Current/Restated") -> #NAME?
A5: SP_ENTITY_NAME | B5: SP_ENTITY_ID | C5: SP_NATIVE_COMPANY_NAME | D5: MI_PRIMARY_INDUSTRY | E5: SP_SHARES_OUT | F5: IQ_EBIT | G5: IQ_EBIT | H5: IQ_EBIT | I5: IQ_EBIT | J5: IQ_EBIT | K5: SP_EBIT_EST | L5: SP_EBIT_EST | M5: IQ_CASH_OPER | N5: IQ_CASH_OPER | O5: IQ_CASH_OPER | P5: IQ_CASH_OPER | Q5: IQ_CASH_OPER | R5: IQ_CASH_INVEST | S5: IQ_CASH_INVEST | T5: IQ_CASH_INVEST | U5: IQ_CASH_INVEST | V5: IQ_CASH_INVEST | W5: IQ_ROE | X5: IQ_ROE | Y5: IQ_ROE | Z5: IQ_ROE | AA5: IQ_ROE | AB5: SP_TICKER | AC5: IQ_PE | AD5: IQ_PBV_X | AE5: SP_EXCHANGE | AF5: IQ_INDUSTRY_GROUP
E6: =SPGLabel(266637,329044,"<>11/06/2025","Options:Curr=JPY,Mag=Standard,ConvMethod=R,FilingVer=Current/Restated") -> #NAME? | F6: FY2021 | G6: FY2022 | H6: FY2023 | I6: FY2024 | J6: FY0 | K6: FY+1 | L6: FY+2 | M6: FY2021 | N6: FY2022 | O6: FY2023 | P6: FY2024 | Q6: FY0 | R6: FY2021 | S6: FY2022 | T6: FY2023 | U6: FY2024 | V6: FY0 | W6: FY2021 | X6: FY2022 | Y6: FY2023 | Z6: FY2024 | AA6: FY0 | AC6: LTM | AD6: LTM
A8: &Do Holdings Co.,Ltd. (TSE:3457) | B8: 4984797 | C8: 株式会社Ａｎｄ Ｄｏホールディングス | D8: Homebuilding Producers | E8: 19957406 | F8: 2589 | G8: 2872 | H8: 3177 | I8: 3588 | J8: 2621 | K8: NA | L8: NA | M8: 12696 | N8: 11983 | O8: -12713 | P8: 7440 | Q8: 7522 | R8: -15289 | S8: -20879 | T8: -6408 | U8: -1309 | V8: -735 | W8: 13.216 | X8: 14.629 | Y8: 15.011 | Z8: 15.17 | AA8: 13.114 | AB8: 3457 | AC8: 8.885326 | AD8: 1.13884 | AE8: TSE | AF8: Consumer Durables and Apparel
A9: 3-D Matrix, Ltd. (TSE:7777) | B9: 4813042 | C9: 株式会社スリー・ディー・マトリックス | D9: Biotechnology | E9: 114260900 | F9: -2649 | G9: -2736 | H9: -3158 | I9: -2117 | J9: -1156 | K9: NA | L9: NA | M9: -3249 | N9: -2903 | O9: -4585 | P9: -1899 | Q9: -1714 | R9: -160 | S9: -79 | T9: -81 | U9: -29 | V9: -33 | W9: -188.654 | X9: -121.488 | Y9: -246.72 | Z9: -58.153 | AA9: -194.782 | AB9: 7777 | AC9: NM | AD9: 13.560043 | AE9: TSE | AF9: Pharmaceuticals, Biotechnology and Life Sciences
A10: 4Cs HD Co., Ltd. (TSE:3726) | B10: 4914111 | C10: 株式会社フォーシーズＨＤ | D10: Other Specialty Retail | E10: 10747248 | F10: -148 | G10: -119 | H10: -215 | I10: -126 | J10: -126 | K10: NA | L10: NA | M10: -106 | N10: -41 | O10: -324 | P10: -361 | Q10: -361 | R10: -8 | S10: -4 | T10: -102 | U10: -50 | V10: -50 | W10: -28.098 | X10: -29.799 | Y10: -56.082 | Z10: -32.327 | AA10: -32.327 | AB10: 3726 | AC10: NM | AD10: 3.52574 | AE10: TSE | AF10: Consumer Discretionary Distribution and Retail
A11: A&A Material Corporation (TSE:5391) | B11: 6333703 | C11: 株式会社エーアンドエーマテリアル | D11: Building Products | E11: 7675364 | F11: 1472 | G11: 1441 | H11: 1491 | I11: 2320 | J11: 1917 | K11: NA | L11: NA | M11: 1076 | N11: 1741 | O11: -694 | P11: 3065 | Q11: 1230 | R11: -1215 | S11: -1654 | T11: -317 | U11: 515 | V11: -2624 | W11: 4.958 | X11: 6.227 | Y11: 5.787 | Z11: 15.235 | AA11: -0.639 | AB11: 5391 | AC11: 90.576797 | AD11: 0.493318 | AE11: TSE | AF11: Capital Goods
A12: A&D HOLON Holdings Company, Limited (TSE:7745) | B12: 4298464 | C12: 株式会社Ａ＆Ｄホロンホールディングス | D12: Electronic Equipment and Instruments | E12: 27373761 | F12: 4405 | G12: 5497 | H12: 7476 | I12: 7956 | J12: 8813 | K12: 9422.5 | L12: 9890 | M12: 5194 | N12: 1782 | O12: 4096 | P12: 7201 | Q12: 6578 | R12: -2222 | S12: -2395 | T12: -1364 | U12: -2007 | V12: -2005 | W12: 17.082 | X12: 15.761 | Y12: 18.576 | Z12: 15.125 | AA12: 16.12 | AB12: 7745 | AC12: 8.355675 | AD12: 1.210617 | AE12: TSE | AF12: Technology Hardware and Equipment
A13: A.D.Works Group Co.,Ltd. (TSE:2982) | B13: 19462280 | C13: 株式会社ＡＤワークスグループ | D13: Real Estate Services | E13: 48530334 | F13: 927 | G13: 1370 | H13: 2435 | I13: 3209 | J13: 3209 | K13: NA | L13: NA | M13: -4435 | N13: -11454 | O13: -683 | P13: 1725 | Q13: 1725 | R13: -151 | S13: 142 | T13: -146 | U13: -329 | V13: -329 | W13: 2.233 | X13: 3.541 | Y13: 8.595 | Z13: 8.936 | AA13: 8.936 | AB13: 2982 | AC13: 9.91753 | AD13: 1.149741 | AE13: TSE | AF13: Real Estate Management and Development
A14: AB&Company Co.,Ltd. (TSE:9251) | B14: 11097415 | C14: 株式会社AB&Company | D14: Specialized Consumer Services | E14: 14246059 | F14: 1526 | G14: 1368 | H14: 1852 | I14: 1679 | J14: 1679 | K14: 1750 | L14: 1850 | M14: 2198 | N14: 2278 | O14: 2714 | P14: 3411 | Q14: 3411 | R14: -426 | S14: -693 | T14: -637 | U14: -700 | V14: -700 | W14: 14.546 | X14: 11.178 | Y14: 13.476 | Z14: 12.654 | AA14: 12.654 | AB14: 9251 | AC14: 15.044273 | AD14: 1.707736 | AE14: TSE | AF14: Consumer Services
A15: Abalance Corporation (TSE:3856) | B15: 4972437 | C15: Ａｂａｌａｎｃｅ株式会社 | D15: Semiconductors | E15: 18903017 | F15: 1362 | G15: 1581 | H15: 12805 | I15: 23268 | J15: 4817.332 | K15: NA | L15: NA | M15: -608 | N15: -6449 | O15: 18526 | P15: 44757 | Q15: -13814.663 | R15: -1391 | S15: -13221 | T15: -20670 | U15: -21191 | V15: -3493.332 | W15: 26.849 | X15: 24.479 | Y15: 77.665 | Z15: 61.972 | AA15: NA | AB15: 3856 | AC15: 14.102888 | AD15: 0.731827 | AE15: TSE | AF15: Semiconductors and Semiconductor Equipment
A16: abc Co., Ltd. (TSE:8783) | B16: 4773566 | C16: ａｂｃ株式会社 | D16: Restaurants | E16: 28912248 | F16: -1465 | G16: -699 | H16: -1914 | I16: -2116 | J16: -2615 | K16: NA | L16: NA | M16: 41 | N16: -965 | O16: -3314 | P16: -1472 | Q16: -2420 | R16: -205 | S16: -235 | T16: -895 | U16: -625 | V16: -3425 | W16: -219.727 | X16: -449.711 | Y16: -256.254 | Z16: -328.963 | AA16: -292.747 | AB16: 8783 | AC16: NM | AD16: 2.200081 | AE16: TSE | AF16: Consumer Services
A17: ABC-Mart,Inc. (TSE:2670) | B17: 4916142 | C17: 株式会社エービーシー・マート | D17: Apparel Retail | E17: 247616642 | F17: 19515 | G17: 27448 | H17: 42302 | I17: 55672 | J17: 62551 | K17: 64822.018 | L17: 67487.047 | M17: 23487 | N17: 25157 | O17: 10882 | P17: 51230 | Q17: 56125 | R17: -11316 | S17: -7458 | T17: -9003 | U17: -11405 | V17: -15103 | W17: 7.039 | X17: 6.198 | Y17: 10.207 | Z17: 12.303 | AA17: 12.782 | AB17: 2670 | AC17: 14.516901 | AD17: 1.738265 | AE17: TSE | AF17: Consumer Discretionary Distribution and Retail
A18: ABEJA, Inc. (TSE:5574) | B18: 5267033 | C18: 株式会社ABEJA | D18: Application Software | E18: 9405600 | F18: -265 | G18: -163 | H18: 403 | I18: 291 | J18: 446 | K18: 480 | L18: 599 | M18: NA | N18: NA | O18: 460 | P18: -760 | Q18: 1621 | R18: NA | S18: NA | T18: -5 | U18: -28 | V18: -28 | W18: NA | X18: -10.376 | Y18: 15.968 | Z18: 5.91 | AA18: 10.707 | AB18: 5574 | AC18: 63.356481 | AD18: 5.972748 | AE18: TSE | AF18: Software and Services
A19: Abhotel Co., Ltd. (TSE:6565) | B19: 6567493 | C19: ＡＢホテル株式会社 | D19: Hotels, Resorts and Cruise Lines | E19: 14175573 | F19: 45 | G19: 959 | H19: 2977 | I19: 3612 | J19: 3963 | K19: NA | L19: NA | M19: -10 | N19: 2056 | O19: 2996 | P19: 2842 | Q19: 3277 | R19: -2065 | S19: -516 | T19: -194 | U19: -1161 | V19: -3778 | W19: 0.166 | X19: 9.052 | Y19: 24.368 | Z19: 24.696 | AA19: 21.931 | AB19: 6565 | AC19: 8.535277 | AD19: 1.737771 | AE19: TSE | AF19: Consumer Services
A20: ABIST Co.,Ltd. (TSE:6087) | B20: 4996292 | C20: 株式会社アビスト | D20: Research and Consulting Services | E20: 3979320 | F20: 429 | G20: 735 | H20: 717.967 | I20: 903.484 | J20: 903.484 | K20: NA | L20: NA | M20: 341 | N20: 711 | O20: 827.91 | P20: 572.35 | Q20: 572.35 | R20: 638 | S20: -44 | T20: 40.86 | U20: 12.136 | V20: 12.136 | W20: 9.361 | X20: 4.92 | Y20: 11.308 | Z20: 9.007 | AA20: 9.007 | AB20: 6087 | AC20: 21.503975 | AD20: 1.817074 | AE20: TSE | AF20: Commercial and Professional Services
A21: Accelia, Inc. (TSE:271A) | B21: 6477405 | D21: Alternative Carriers | E21: 834000 | F21: NA | G21: NA | H21: 12 | I21: 30 | J21: 1 | K21: NA | L21: NA | M21: NA | N21: NA | O21: NA | P21: NA | Q21: -33 | R21: NA | S21: NA | T21: NA | U21: NA | V21: -31 | W21: NA | X21: NA | Y21: NA | Z21: 4.054 | AA21: 0 | AB21: 271A | AC21: NM | AD21: NA | AE21: TSE | AF21: Telecommunication Services
A22: Access Co., Ltd. (TSE:4813) | B22: 4207883 | C22: 株式会社ＡＣＣＥＳＳ | D22: Application Software | E22: 37787430 | F22: -2120 | G22: -3207 | H22: -1510 | I22: -1978 | J22: -2260 | K22: NA | L22: NA | M22: 302 | N22: -370 | O22: -909 | P22: 96 | Q22: 1134 | R22: -2621 | S22: -1335 | T22: -1056 | U22: -1571 | V22: -1068 | W22: -8.576 | X22: -14.75 | Y22: -13.174 | Z22: -13.967 | AA22: -42.77 | AB22: 4813 | AC22: NM | AD22: 2.756604 | AE22: TSE | AF22: Software and Services
A23: Access Group Holdings Co., Ltd. (TSE:7042) | B23: 6840415 | C23: 株式会社アクセスグループ・ホールディングス | D23: Advertising | E23: 3210410 | F23: -226 | G23: 55 | H23: 181 | I23: 89 | J23: 230 | K23: NA | L23: NA | M23: -436 | N23: -20 | O23: -138 | P23: 244 | Q23: 190 | R23: 56 | S23: 269 | T23: 216 | U23: 22 | V23: 43 | W23: -66.667 | X23: 2.483 | Y23: NA | Z23: 18.829 | AA23: 18.477 | AB23: 7042 | AC23: 12.227212 | AD23: 1.624926 | AE23: TSE | AF23: Media and Entertainment
A24: Accrete Inc. (TSE:4395) | B24: 7709174 | C24: 株式会社アクリート | D24: Wireless Telecommunication Services | E24: 6769884 | F24: 466 | G24: 1172 | H24: 310 | I24: 331 | J24: 331 | K24: NA | L24: NA | M24: 359 | N24: 976 | O24: 191 | P24: 214 | Q24: 214 | R24: -464 | S24: -471 | T24: -95 | U24: -104 | V24: -104 | W24: NA | X24: 43.542 | Y24: -1.157 | Z24: -5.196 | AA24: -5.196 | AB24: 4395 | AC24: 41.268729 | AD24: 2.526438 | AE24: TSE | AF24: Telecommunication Services
A25: Achilles Corporation (TSE:5142) | B25: 4986666 | C25: アキレス株式会社 | D25: Commodity Chemicals | E25: 13666949 | F25: 1571 | G25: 856 | H25: -712 | I25: -959 | J25: -436 | K25: NA | L25: NA | M25: 4509 | N25: 4707 | O25: -1072 | P25: 1878 | Q25: 2686 | R25: -2830 | S25: -5030 | T25: -4484 | U25: -3793 | V25: -1918 | W25: 7.329 | X25: 3.241 | Y25: -2.564 | Z25: -19.148 | AA25: 1.083 | AB25: 5142 | AC25: 22.887734 | AD25: 0.416417 | AE25: TSE | AF25: Materials
A26: Acmos Inc. (TSE:6888) | B26: 4545341 | C26: アクモス株式会社 | D26: Application Software | E26: 9948057 | F26: 501 | G26: 472 | H26: 650 | I26: 661 | J26: 584 | K26: NA | L26: NA | M26: 290 | N26: 358 | O26: 626 | P26: 347 | Q26: 256 | R26: -26 | S26: -341 | T26: -118 | U26: -230 | V26: -13 | W26: 15.967 | X26: 11.688 | Y26: 14.917 | Z26: 13.529 | AA26: 11.37 | AB26: 6888 | AC26: 14.735021 | AD26: 1.70871 | AE26: TSE | AF26: Software and Services
A27: Acom Co., Ltd. (TSE:8572) | B27: 4250356 | C27: アコム株式会社 | D27: Specialty Finance: Consumer Focused | E27: 1566613978 | F27: 98897 | G27: 34779 | H27: 91303 | I27: 91280 | J27: 64314 | K27: 95288.378 | L27: 100760.05 | M27: 113179 | N27: 46089 | O27: -1318 | P27: -36759 | Q27: 876 | R27: -4566 | S27: -4032 | T27: -2692 | U27: -6178 | V27: -6478 | W27: 17.469 | X27: 11.085 | Y27: 10.048 | Z27: 8.937 | AA27: 5.288 | AB27: 8572 | AC27: 13.349016 | AD27: 1.049313 | AE27: TSE | AF27: Financial Services
A28: ACSL Ltd. (TSE:6232) | B28: 6322700 | C28: 株式会社ＡＣＳＬ | D28: Electronic Equipment and Instruments | E28: 15924439 | F28: -1585.333 | G28: -2203 | H28: -2071 | I28: -2293 | J28: -2293 | K28: -1400 | L28: -700 | M28: -1793.333 | N28: -2148 | O28: -2572 | P28: -1902 | Q28: -1902 | R28: -1001.333 | S28: -271 | T28: -94 | U28: -46 | V28: -46 | W28: NA | X28: -62.062 | Y28: -97.865 | Z28: -193.078 | AA28: -193.078 | AB28: 6232 | AC28: NM | AD28: 29.037746 | AE28: TSE | AF28: Technology Hardware and Equipment
A29: ACTBE Inc. (TSE:439A) | B29: 113256625 | D29: IT Consulting and Other Services | E29: 100000 | F29: NA | G29: NA | H29: NA | I29: NA | J29: 35 | K29: NA | L29: NA | M29: NA | N29: NA | O29: NA | P29: NA | Q29: NA | R29: NA | S29: NA | T29: NA | U29: NA | V29: NA | W29: NA | X29: NA | Y29: NA | Z29: NA | AA29: NA | AB29: 439A | AC29: 23.809524 | AD29: NA | AE29: TSE | AF29: Software and Services
A30: Adeka Corporation (TSE:4401) | B30: 6354598 | C30: 株式会社ＡＤＥＫＡ | D30: Commodity Chemicals | E30: 100330297 | F30: 28980 | G30: 34928 | H30: 32371 | I30: 35429 | J30: 41011 | K30: 42757.143 | L30: 46257.143 | M30: 36872 | N30: 21367 | O30: 17253 | P30: 41954 | Q30: 46235 | R30: -14189 | S30: -11317 | T30: -19520 | U30: -23069 | V30: -12553 | W30: 7.447 | X30: 9.629 | Y30: 6.888 | Z30: 8.078 | AA30: 8.248 | AB30: 4401 | AC30: 14.138828 | AD30: 1.196395 | AE30: TSE | AF30: Materials
A31: adish Co., Ltd. (TSE:7093) | B31: 9831689 | C31: アディッシュ株式会社 | D31: Internet Services and Infrastructure | E31: 1964560 | F31: 52 | G31: 98 | H31: -172 | I31: -132 | J31: -132 | K31: NA | L31: NA | M31: 112 | N31: 93 | O31: -249 | P31: -186 | Q31: -186 | R31: -55 | S31: -15 | T31: -14 | U31: -16 | V31: -16 | W31: 7.799 | X31: 11.241 | Y31: -33.333 | Z31: -29.151 | AA31: -29.151 | AB31: 7093 | AC31: NM | AD31: 2.796235 | AE31: TSE | AF31: Software and Services
A32: Adjuvant Holdings Co.,Ltd. (TSE:4929) | B32: 4916932 | C32: 株式会社アジュバンホールディングス | D32: Personal Care and Beauty Products: Producers | E32: 8000395 | F32: 294 | G32: 391 | H32: 233 | I32: -1 | J32: 127 | K32: NA | L32: NA | M32: 403 | N32: 417 | O32: -321 | P32: 377 | Q32: 307 | R32: -235 | S32: 24 | T32: 344 | U32: 391 | V32: -95 | W32: 3.457 | X32: 9.347 | Y32: 9.155 | Z32: -2.275 | AA32: 0.953 | AB32: 4929 | AC32: 164.17587 | AD32: 1.481988 | AE32: TSE | AF32: Household and Personal Products
A33: ADR120S, Inc. (TSE:3750) | B33: 4989711 | C33: 株式会社ＡＤＲ１２０Ｓ | D33: Diversified Real Estate Activities | E33: 8928219 | F33: -731 | G33: -462 | H33: -795 | I33: -773 | J33: -807 | K33: NA | L33: NA | M33: -82 | N33: -187 | O33: -39 | P33: -1152 | Q33: -987 | R33: 6 | S33: -216 | T33: -283 | U33: 8689 | V33: 22 | W33: -21.008 | X33: -2.121 | Y33: -33.244 | Z33: 5.064 | AA33: -125 | AB33: 3750 | AC33: NM | AD33: 15.331699 | AE33: TSE | AF33: Real Estate Management and Development
A34: Ad-Sol Nissin Corporation (TSE:3837) | B34: 4970320 | C34: アドソル日進株式会社 | D34: IT Consulting and Other Services | E34: 17459596 | F34: 1285 | G34: 1088 | H34: 1211 | I34: 1438 | J34: 1711 | K34: 1900 | L34: 2100 | M34: 187 | N34: 1781 | O34: 1020 | P34: 804 | Q34: 1027 | R34: -6 | S34: -241 | T34: -99 | U34: -71 | V34: -202 | W34: NA | X34: 13.88 | Y34: 13.305 | Z34: 14.022 | AA34: 16.836 | AB34: 3837 | AC34: 18.880746 | AD34: 3.226916 | AE34: TSE | AF34: Software and Services
A35: Adtec Plasma Technology Co., Ltd. (TSE:6668) | B35: 4545709 | C35: 株式会社アドテック プラズマ テクノロジー | D35: Electronic Equipment and Instruments | E35: 8567267 | F35: 1103 | G35: 2736 | H35: 2242 | I35: 1486 | J35: 1809 | K35: NA | L35: NA | M35: -185 | N35: -1583 | O35: -1501 | P35: 3032 | Q35: 3364 | R35: -226 | S35: -1709 | T35: -1935 | U35: -937 | V35: -259 | W35: 13.851 | X35: 27.455 | Y35: 16.782 | Z35: 10.565 | AA35: 15.881 | AB35: 6668 | AC35: 5.251886 | AD35: 0.800175 | AE35: TSE | AF35: Technology Hardware and Equipment
A36: Advan Group Co., Ltd. (TSE:7463) | B36: 4993150 | C36: 株式会社アドヴァングループ | D36: Trading Companies and Distributors | E36: 34101145 | F36: 4086 | G36: 3828 | H36: 4702 | I36: 3939 | J36: 3151 | K36: NA | L36: NA | M36: 5457 | N36: 3209 | O36: 3753 | P36: 4967 | Q36: 1890 | R36: -4676 | S36: -506 | T36: -8091 | U36: -5582 | V36: 1186 | W36: 6.667 | X36: 9.162 | Y36: 7.914 | Z36: 22.404 | AA36: 11.623 | AB36: 7463 | AC36: 4.071104 | AD36: 0.543924 | AE36: TSE | AF36: Capital Goods
A37: Advance Create Co., Ltd. (TSE:8798) | B37: 5000326 | C37: 株式会社アドバンスクリエイト | D37: Insurance Broker | E37: 31896771 | F37: 891 | G37: 95 | H37: -1303 | I37: -712 | J37: -712 | K37: NA | L37: NA | M37: 1643 | N37: 364 | O37: -206 | P37: -1674 | Q37: -1674 | R37: -485 | S37: -391 | T37: -668 | U37: -117 | V37: -117 | W37: 3.757 | X37: -65.599 | Y37: 325.267 | Z37: 61.61 | AA37: 61.61 | AB37: 8798 | AC37: NM | AD37: NM | AE37: TSE | AF37: Insurance
A38: Advanced Media, Inc. (TSE:3773) | B38: 4970714 | C38: 株式会社アドバンスト・メディア | D38: Application Software | E38: 15600391 | F38: 680 | G38: 812 | H38: 1081 | I38: 1359 | J38: 1443 | K38: 1290 | L38: 1320 | M38: 1232 | N38: 1149 | O38: 1266 | P38: 1494 | Q38: 1432 | R38: -402 | S38: -367 | T38: -2861 | U38: -1270 | V38: -1069 | W38: 5.666 | X38: 3.855 | Y38: 8.093 | Z38: 9.588 | AA38: 11.95 | AB38: 3773 | AC38: 10.877955 | AD38: 1.281781 | AE38: TSE | AF38: Software and Services
A39: Advanex Inc. (TSE:5998) | B39: 4992625 | C39: 株式会社アドバネクス | D39: Machinery and Supplies and Components: Industrial | E39: 4105745 | F39: 176 | G39: 148 | H39: 61 | I39: 387 | J39: 1109 | K39: 1400 | L39: 1700 | M39: 1404 | N39: 945 | O39: 279 | P39: 2048 | Q39: 509 | R39: 327 | S39: -1557 | T39: -1599 | U39: -667 | V39: -1302 | W39: 11.182 | X39: -1.238 | Y39: 0.849 | Z39: 3.456 | AA39: -7.668 | AB39: 5998 | AC39: NM | AD39: 0.823195 | AE39: TSE | AF39: Capital Goods
A40: Advantage Risk Management Co., Ltd. (TSE:8769) | B40: 4812978 | C40: 株式会社アドバンテッジリスクマネジメント | D40: Health Care Services | E40: 15697546 | F40: 727 | G40: 353 | H40: 553 | I40: 726 | J40: 1023 | K40: NA | L40: NA | M40: 712 | N40: 578 | O40: 931 | P40: 1292 | Q40: 1705 | R40: -772 | S40: -2148 | T40: -219 | U40: -948 | V40: -2262 | W40: 14.041 | X40: 5.648 | Y40: 10.674 | Z40: 13.256 | AA40: 18.743 | AB40: 8769 | AC40: 13.349683 | AD40: 2.663615 | AE40: TSE | AF40: Health Care Equipment and Services
A41: Advantest Corporation (TSE:6857) | B41: 4228826 | C41: 株式会社アドバンテスト | D41: Semiconductor Materials and Equipment | E41: 727392176 | F41: 68275 | G41: 114734 | H41: 167687 | I41: 90626 | J41: 249554 | K41: 360320.72 | L41: 415033.71 | M41: 67830 | N41: 78889 | O41: 70224 | P41: 32668 | Q41: 285971 | R41: -16831 | S41: -46907 | T41: -26706 | U41: -27940 | V41: -42189 | W41: 27.27 | X41: 30.366 | Y41: 39.318 | Z41: 15.575 | AA41: 34.376 | AB41: 6857 | AC41: 56.133483 | AD41: 23.787958 | AE41: TSE | AF41: Semiconductors and Semiconductor Equipment
A42: Adventure, Inc. (TSE:6030) | B42: 4980613 | C42: 株式会社アドベンチャー | D42: Hotels, Resorts and Cruise Lines | E42: 7435578 | F42: 820 | G42: 1983 | H42: 2881 | I42: 1589 | J42: 1085 | K42: NA | L42: NA | M42: -251 | N42: 2999 | O42: 3040 | P42: 856 | Q42: 2220 | R42: -628 | S42: 351 | T42: -895 | U42: -295 | V42: -1139 | W42: 39.43 | X42: 22.366 | Y42: 17.406 | Z42: 5.93 | AA42: -19.364 | AB42: 6030 | AC42: NM | AD42: 1.871203 | AE42: TSE | AF42: Consumer Services
A43: Adways Inc. (TSE:2489) | B43: 4993415 | C43: 株式会社アドウェイズ | D43: Advertising | E43: 39082120 | F43: 1842 | G43: 1183 | H43: 922 | I43: 159 | J43: 159 | K43: NA | L43: NA | M43: 1232 | N43: 385 | O43: 592 | P43: 185 | Q43: 185 | R43: -289.333 | S43: 1957 | T43: -95 | U43: 155 | V43: 155 | W43: NA | X43: 16.592 | Y43: 5.97 | Z43: -3.083 | AA43: -3.083 | AB43: 2489 | AC43: NM | AD43: 0.860196 | AE43: TSE | AF43: Media and Entertainment
A44: Aeon Co., Ltd. (TSE:8267) | B44: 4160743 | C44: イオン株式会社 | D44: Consumer Staples Merchandise Retail | E44: 2766798546 | F44: 151054 | G44: 174799 | H44: 210347 | I44: 251335 | J44: 238047 | K44: 274930.1 | L44: 322280.81 | M44: 396461 | N44: 204452 | O44: 433710 | P44: 368487 | Q44: 566218 | R44: -341814 | S44: -343854 | T44: -335123 | U44: -508876 | V44: -478810 | W44: -2.096 | X44: 3.25 | Y44: 4.461 | Z44: 5.169 | AA44: 3.39 | AB44: 8267 | AC44: 218.43362 | AD44: 5.249314 | AE44: TSE | AF44: Consumer Staples Distribution and Retail
A45: AEON Fantasy Co.,LTD. (TSE:4343) | B45: 4626508 | C45: 株式会社イオンファンタジー | D45: Leisure Facilities | E45: 19779671 | F45: -7429 | G45: -3408 | H45: 849 | I45: 3585 | J45: 4345 | K45: 7400 | L45: 8550 | M45: 183 | N45: 6176 | O45: 9057 | P45: 12056 | Q45: 12353 | R45: -6964 | S45: -7091 | T45: -4845 | U45: -10725 | V45: -10858 | W45: -43.178 | X45: -31.853 | Y45: -33.505 | Z45: 16.154 | AA45: -23.474 | AB45: 4343 | AC45: NM | AD45: 6.704498 | AE45: TSE | AF45: Consumer Services
A46: AEON Financial Service Co., Ltd. (TSE:8570) | B46: 4329529 | C46: イオンフィナンシャルサービス株式会社 | D46: Specialty Finance: Consumer Focused | E46: 215884387 | F46: NA | G46: NA | H46: NA | I46: NA | J46: NA | K46: 58486.752 | L46: 66148.3 | M46: -176829 | N46: -82282 | O46: -117402 | P46: -191950 | Q46: -338712 | R46: -94557 | S46: -33562 | T46: 10981 | U46: -113697 | V46: -158479 | W46: 5.592 | X46: 8.345 | Y46: 8.307 | Z46: 6.044 | AA46: 5.576 | AB46: 8570 | AC46: 18.083669 | AD46: 0.719545 | AE46: TSE | AF46: Financial Services
A47: Aeon Hokkaido Corporation (TSE:7512) | B47: 4546016 | C47: イオン北海道株式会社 | D47: Food Retail | E47: 139457984 | F47: NA | G47: NA | H47: NA | I47: NA | J47: 2549 | K47: NA | L47: NA | M47: NA | N47: NA | O47: NA | P47: NA | Q47: 7857 | R47: NA | S47: NA | T47: NA | U47: NA | V47: -3740 | W47: NA | X47: NA | Y47: NA | Z47: NA | AA47: 6.372 | AB47: 7512 | AC47: 42.568718 | AD47: 1.597435 | AE47: TSE | AF47: Consumer Staples Distribution and Retail
A48: Aeon Kyushu Co., Ltd. (TSE:2653) | B48: 4160741 | C48: イオン九州株式会社 | D48: Broadline Retail | E48: 34130103 | F48: NA | G48: NA | H48: NA | I48: 10382 | J48: 10537 | K48: NA | L48: NA | M48: NA | N48: NA | O48: NA | P48: 14616 | Q48: 14426 | R48: NA | S48: NA | T48: NA | U48: -11630 | V48: -17354 | W48: NA | X48: NA | Y48: NA | Z48: NA | AA48: 10.592 | AB48: 2653 | AC48: 12.975871 | AD48: 1.706505 | AE48: TSE | AF48: Consumer Discretionary Distribution and Retail
A49: Aeria Inc. (TSE:3758) | B49: 4233025 | C49: 株式会社アエリア | D49: Interactive Home Entertainment | E49: 20833054 | F49: 840 | G49: 846 | H49: 477 | I49: -42 | J49: -42 | K49: NA | L49: NA | M49: 2048 | N49: -1085 | O49: -1975 | P49: -327 | Q49: -327 | R49: 159 | S49: -51 | T49: 168 | U49: -464 | V49: -464 | W49: 5.995 | X49: 2.093 | Y49: 5.166 | Z49: -7.755 | AA49: -7.755 | AB49: 3758 | AC49: NM | AD49: 0.694681 | AE49: TSE | AF49: Media and Entertainment
A50: Aero Lab International Inc. (TSE:326A) | B50: 113619268 | D50: Airport Services | E50: 325000 | F50: NA | G50: NA | H50: 69 | I50: -93 | J50: 93 | K50: NA | L50: NA | M50: NA | N50: NA | O50: NA | P50: NA | Q50: -138 | R50: NA | S50: NA | T50: NA | U50: NA | V50: -101 | W50: NA | X50: NA | Y50: NA | Z50: -34.437 | AA50: 62.295 | AB50: 326A | AC50: NM | AD50: NA | AE50: TSE | AF50: Transportation
A51: AeroEdge Co., Ltd. (TSE:7409) | B51: 10417907 | C51: AeroEdge株式会社 | D51: Aerospace and Defense | E51: 3842379 | F51: -845 | G51: -124 | H51: 479 | I51: 706 | J51: 655 | K51: NA | L51: NA | M51: NA | N51: NA | O51: 1077 | P51: 1391 | Q51: 1333 | R51: NA | S51: NA | T51: -137 | U51: -1526 | V51: -1952 | W51: NA | X51: 0.723 | Y51: 52.272 | Z51: 29.608 | AA51: 21.022 | AB51: 7409 | AC51: 34.82616 | AD51: 5.908565 | AE51: TSE | AF51: Capital Goods
A52: AFC-HD AMS Life Science Co., Ltd. (TSE:2927) | B52: 4546022 | C52: 株式会社ＡＦＣ-ＨＤアムスライフサイエンス | D52: Personal Care and Beauty Products: Producers | E52: 14091105 | F52: 2246 | G52: 1012 | H52: 1637 | I52: 1916 | J52: 2410 | K52: NA | L52: NA | M52: 2582 | N52: 1492 | O52: 865 | P52: 1540 | Q52: 1854 | R52: -274 | S52: -1077 | T52: -1946 | U52: -2761 | V52: -3394 | W52: 12.93 | X52: 5.872 | Y52: 8.641 | Z52: 9.192 | AA52: 10.071 | AB52: 2927 | AC52: 8.237968 | AD52: 0.792654 | AE52: TSE | AF52: Household and Personal Products
A53: AGC Inc. (TSE:5201) | B53: 6333234 | C53: ＡＧＣ株式会社 | D53: Building Products | E53: 212358940 | F53: 203990 | G53: 183377 | H53: 130630 | I53: 118617 | J53: 118617 | K53: 123226.59 | L53: 154843.83 | M53: 326713 | N53: 217146 | O53: 212546 | P53: 284815 | Q53: 284815 | R53: -123787 | S53: -145312 | T53: -179790 | U53: -195583 | V53: -195583 | W53: 11.677 | X53: 1.468 | Y53: 5.092 | Z53: -4.686 | AA53: -4.686 | AB53: 5201 | AC53: 20.994249 | AD53: 0.772315 | AE53: TSE | AF53: Capital Goods
A54: AGEHA Inc. (TSE:9330) | B54: 10499704 | C54: 株式会社揚羽 | D54: Advertising | E54: 1428500 | F54: NA | G54: NA | H54: NA | I54: NA | J54: NA | K54: NA | L54: NA | M54: NA | N54: NA | O54: NA | P54: NA | Q54: NA | R54: NA | S54: NA | T54: NA | U54: NA | V54: NA | W54: NA | X54: NA | Y54: NA | Z54: NA | AA54: NA | AB54: 9330 | AC54: NA | AD54: NA | AE54: TSE | AF54: Media and Entertainment
A55: Agile Media Network Inc. (TSE:6573) | B55: 6471802 | C55: アジャイルメディア・ネットワーク株式会社 | D55: Interactive Media and Services | E55: 32755720 | F55: -107 | G55: -223 | H55: -406 | I55: -302 | J55: -302 | K55: NA | L55: NA | M55: -217 | N55: -515 | O55: -577 | P55: -266 | Q55: -266 | R55: -32 | S55: 28 | T55: -99 | U55: -79 | V55: -79 | W55: -954.839 | X55: 155.556 | Y55: -547.541 | Z55: -147.345 | AA55: -147.345 | AB55: 6573 | AC55: NM | AD55: 5.552783 | AE55: TSE | AF55: Media and Entertainment
A56: AGORA Hospitality Group Co., Ltd (TSE:9704) | B56: 4217808 | C56: 株式会社アゴーラホスピタリティーグループ | D56: Hotels, Resorts and Cruise Lines | E56: 266703960 | F56: -1413 | G56: -1433 | H56: -110 | I56: 261 | J56: 261 | K56: NA | L56: NA | M56: -373 | N56: 240 | O56: 394 | P56: 435 | Q56: 435 | R56: -4 | S56: -763 | T56: -617 | U56: -2625 | V56: -2625 | W56: -25.186 | X56: -24.464 | Y56: -3.567 | Z56: 2.903 | AA56: 2.903 | AB56: 9704 | AC56: 59.716599 | AD56: 3.5163 | AE56: TSE | AF56: Consumer Services
A57: Agratio urban design Inc. (TSE:3467) | B57: 4984819 | C57: アグレ都市デザイン株式会社 | D57: Homebuilding Producers | E57: 5753697 | F57: NA | G57: NA | H57: NA | I57: 1611 | J57: 2549 | K57: NA | L57: NA | M57: NA | N57: NA | O57: NA | P57: -588 | Q57: -4555 | R57: NA | S57: NA | T57: NA | U57: -493 | V57: 37 | W57: NA | X57: NA | Y57: NA | Z57: NA | AA57: 23.901 | AB57: 3467 | AC57: 7.369458 | AD57: 1.856672 | AE57: TSE | AF57: Consumer Durables and Apparel
A58: AGS Corporation (TSE:3648) | B58: 4971327 | C58: ＡＧＳ株式会社 | D58: IT Consulting and Other Services | E58: 16714442 | F58: 769 | G58: 949 | H58: 874 | I58: 1273 | J58: 1850 | K58: NA | L58: NA | M58: 1747 | N58: 2123 | O58: 1711 | P58: 2505 | Q58: 742 | R58: -702 | S58: -518 | T58: -475 | U58: -595 | V58: -608 | W58: 4.058 | X58: 5.022 | Y58: 5.177 | Z58: 6.859 | AA58: 9.673 | AB58: 3648 | AC58: 11.562657 | AD58: 1.471756 | AE58: TSE | AF58: Software and Services
A59: AHC Group Inc. (TSE:7083) | B59: 19775910 | C59: ＡＨＣグループ株式会社 | D59: Specialized Consumer Services | E59: 2107493 | F59: -234 | G59: -219 | H59: 15 | I59: 142 | J59: 142 | K59: NA | L59: NA | M59: -12 | N59: -102 | O59: 97 | P59: 439 | Q59: 439 | R59: -670 | S59: -909 | T59: -94 | U59: -358 | V59: -358 | W59: 0.074 | X59: -20.944 | Y59: 5.977 | Z59: 8.302 | AA59: 8.302 | AB59: 7083 | AC59: 36.544997 | AD59: 1.408398 | AE59: TSE | AF59: Consumer Services
A60: Ahjikan Co., Ltd. (TSE:2907) | B60: 4251525 | C60: 株式会社あじかん | D60: Packaged Foods and Meats Producers | E60: 7610947 | F60: 632 | G60: 560 | H60: 89 | I60: 1710 | J60: 1965 | K60: NA | L60: NA | M60: 2002 | N60: 442 | O60: 959 | P60: 1376 | Q60: 3455 | R60: -238 | S60: -438 | T60: -533 | U60: -1100 | V60: -763 | W60: 4.637 | X60: 4.686 | Y60: 1.905 | Z60: 10.06 | AA60: 9.316 | AB60: 2907 | AC60: 9.190035 | AD60: 0.549424 | AE60: TSE | AF60: Food, Beverage and Tobacco
A61: Ahresty Corporation (TSE:5852) | B61: 4916285 | C61: 株式会社アーレスティ | D61: Automotive Parts and Equipment | E61: 24801156 | F61: -2553 | G61: -2422 | H61: 24 | I61: 2291 | J61: 3372 | K61: 5400 | L61: 6000 | M61: 7942 | N61: 8259 | O61: 10727 | P61: 18319 | Q61: 15308 | R61: -11570 | S61: -6083 | T61: -6331 | U61: -13939 | V61: -12889 | W61: -5.032 | X61: -9.504 | Y61: -0.152 | Z61: -14.223 | AA61: -5.583 | AB61: 5852 | AC61: NM | AD61: 0.389697 | AE61: TSE | AF61: Automobiles and Components
A62: AI CROSS Inc. (TSE:4476) | B62: 7337268 | C62: AI CROSS株式会社 | D62: Application Software | E62: 3758446 | F62: 260 | G62: 224 | H62: 292 | I62: 335 | J62: 335 | K62: NA | L62: NA | M62: 187 | N62: -4 | O62: 360 | P62: 342 | Q62: 342 | R62: 96 | S62: -94 | T62: -29 | U62: -24 | V62: -24 | W62: NA | X62: 5.997 | Y62: 9.42 | Z62: 8.739 | AA62: 8.739 | AB62: 4476 | AC62: 74.045671 | AD62: 3.636189 | AE62: TSE | AF62: Software and Services
A63: Ai Fusion Capital Group Corp. (TSE:254A) | B63: 4772411 | C63: ミライドア株式会社 | D63: Asset Management | E63: 7965225 | F63: -14 | G63: 66 | H63: 53 | I63: -49 | J63: -49 | K63: NA | L63: NA | M63: 277 | N63: 228 | O63: 190 | P63: -4 | Q63: -4 | R63: -12 | S63: -42 | T63: 399 | U63: 1309 | V63: 1309 | W63: 3.219 | X63: 5.228 | Y63: 32.353 | Z63: 26.23 | AA63: 26.23 | AB63: 254A | AC63: NM | AD63: 2.010977 | AE63: TSE | AF63: Financial Services
A64: Ai Holdings Corporation (TSE:3076) | B64: 4967992 | C64: あい ホールディングス株式会社 | D64: Electronic Equipment and Instruments | E64: 53273695 | F64: 9449 | G64: 9851 | H64: 9600 | I64: 9810 | J64: 8890 | K64: 10700 | L64: 11100 | M64: 9372 | N64: 8095 | O64: 4541 | P64: 8432 | Q64: 7647 | R64: -656 | S64: -2207 | T64: -1314 | U64: -6428 | V64: 7084 | W64: 11.373 | X64: 13.465 | Y64: 12.832 | Z64: 21.381 | AA64: 22.103 | AB64: 3076 | AC64: 6.491864 | AD64: 1.285363 | AE64: TSE | AF64: Technology Hardware and Equipment
A65: AI inside Inc. (TSE:4488) | B65: 5313695 | C65: AI inside 株式会社 | D65: Application Software | E65: 3965532 | F65: 2361 | G65: 569 | H65: 284 | I65: 448 | J65: 385 | K65: NA | L65: NA | M65: 2090 | N65: -208 | O65: 793 | P65: 737 | Q65: 778 | R65: -1503 | S65: -223 | T65: -2068 | U65: 597 | V65: -200 | W65: 51.014 | X65: 9.202 | Y65: -11.405 | Z65: 11.492 | AA65: -10.485 | AB65: 4488 | AC65: NM | AD65: 2.491557 | AE65: TSE | AF65: Software and Services
A66: AI Partners Financial Inc. (TSE:7345) | B66: 27861046 | C66: 株式会社アイ・パートナーズ フィナンシャル | D66: Investment Banks, Brokers and Capital Markets | E66: 3272000 | F66: 246 | G66: 116 | H66: -121 | I66: 14 | J66: -2 | K66: NA | L66: NA | M66: 311 | N66: -60 | O66: -61 | P66: 14 | Q66: -3 | R66: -19 | S66: -35 | T66: -12 | U66: -6 | V66: -5 | W66: 36.277 | X66: 9.384 | Y66: -17.409 | Z66: 1.103 | AA66: -1.424 | AB66: 7345 | AC66: NM | AD66: 3.331687 | AE66: TSE | AF66: Financial Services
A67: Ai Robotics Inc. (TSE:247A) | B67: 5329740 | C67: Aiロボティクス株式会社 | D67: Advertising | E67: 58389950 | F67: NA | G67: NA | H67: 306.386 | I67: 1256.996 | J67: 2480.289 | K67: 4555 | L67: 7225 | M67: NA | N67: NA | O67: 10.907 | P67: 900.175 | Q67: 1316.195 | R67: NA | S67: NA | T67: 0.184 | U67: -89.686 | V67: -158.536 | W67: NA | X67: NA | Y67: NA | Z67: 115.167 | AA67: 76.741 | AB67: 247A | AC67: 103.10762 | AD67: 36.632685 | AE67: TSE | AF67: Media and Entertainment
A68: AI storm Co., Ltd. (TSE:3719) | B68: 4996817 | C68: ＡＩストーム株式会社 | D68: Research and Consulting Services | E68: 25765232 | F68: -92 | G68: NA | H68: NA | I68: NA | J68: -92 | K68: NA | L68: NA | M68: -73 | N68: NA | O68: NA | P68: NA | Q68: -73 | R68: -40 | S68: NA | T68: NA | U68: NA | V68: -40 | W68: NA | X68: NA | Y68: NA | Z68: NA | AA68: NA | AB68: 3719 | AC68: NM | AD68: 9.935123 | AE68: TSE | AF68: Commercial and Professional Services
A69: AI,Inc. (TSE:4388) | B69: 7380451 | C69: 株式会社エーアイ | D69: Application Software | E69: 6587627 | F69: NA | G69: NA | H69: NA | I69: NA | J69: 109 | K69: NA | L69: NA | M69: NA | N69: NA | O69: NA | P69: NA | Q69: 101 | R69: NA | S69: NA | T69: NA | U69: NA | V69: -245 | W69: NA | X69: NA | Y69: NA | Z69: NA | AA69: NA | AB69: 4388 | AC69: NM | AD69: 1.341185 | AE69: TSE | AF69: Software and Services
A70: AIAI Group Corporation (TSE:6557) | B70: 8382031 | C70: ＡＩＡＩグループ株式会社 | D70: Specialized Consumer Services | E70: 6592136 | F70: -437 | G70: -311 | H70: 81 | I70: 533 | J70: 734 | K70: NA | L70: NA | M70: 850 | N70: 476 | O70: 873 | P70: 1767 | Q70: 1393 | R70: -1491 | S70: -1368.8 | T70: -809 | U70: -619 | V70: -424 | W70: -4.579 | X70: NA | Y70: -34.551 | Z70: 22.907 | AA70: 18.469 | AB70: 6557 | AC70: 19.379364 | AD70: 3.219444 | AE70: TSE | AF70: Consumer Services
A71: Aica Kogyo Company, Limited (TSE:4206) | B71: 4264988 | C71: アイカ工業株式会社 | D71: Specialty Chemicals | E71: 61140500 | F71: 17992 | G71: 20349 | H71: 20557 | I71: 25287 | J71: 27409 | K71: 29525 | L71: 31550 | M71: 19713 | N71: 11685 | O71: 19852 | P71: 28482 | Q71: 26751 | R71: -9756 | S71: -8342 | T71: -9061 | U71: -7574 | V71: -11121 | W71: 8.129 | X71: 9.187 | Y71: 6.812 | Z71: 10.011 | AA71: 10.212 | AB71: 4206 | AC71: 14.19788 | AD71: 1.248069 | AE71: TSE | AF71: Materials
A72: Aichi Corporation (TSE:6345) | B72: 4996047 | C72: 株式会社アイチコーポレーション | D72: Machinery and Equipment: Construction and Heavy Transportation | E72: 64559841 | F72: 7051 | G72: 6862 | H72: 7351 | I72: 6342 | J72: 7440 | K72: 7900 | L72: 8550 | M72: 10873 | N72: 3989 | O72: 4508 | P72: 7111 | Q72: 9871 | R72: -10655 | S72: 997 | T72: -2253 | U72: 32763 | V72: -1955 | W72: 8.362 | X72: 7.557 | Y72: 7.707 | Z72: 6.573 | AA72: 7.64 | AB72: 6345 | AC72: 15.084346 | AD72: 1.197456 | AE72: TSE | AF72: Capital Goods
A73: Aichi Financial Group, Inc. (TSE:7389) | B73: 106378376 | C73: 株式会社あいちフィナンシャルグループ | D73: Bank | E73: 48704445 | F73: NA | G73: NA | H73: NA | I73: NA | J73: NA | K73: NA | L73: NA | M73: NA | N73: NA | O73: -317411 | P73: -374975 | Q73: -194569 | R73: NA | S73: NA | T73: 33031 | U73: 64784 | V73: 117584 | W73: NA | X73: NA | Y73: NA | Z73: 2.381 | AA73: 2.481 | AB73: 7389 | AC73: 25.679909 | AD73: 0.546632 | AE73: TSE | AF73: Banks
A74: Aichi Steel Corporation (TSE:5482) | B74: 6333634 | C74: 愛知製鋼株式会社 | D74: Steel | E74: 64004316 | F74: 3564 | G74: 3328 | H74: 4041 | I74: 12477 | J74: 12708 | K74: NA | L74: NA | M74: 14793 | N74: 5210 | O74: 13028 | P74: 33817 | Q74: 25354 | R74: -13834 | S74: -15542 | T74: -15958 | U74: -18895 | V74: -17918 | W74: 2.303 | X74: 1.085 | Y74: 1.345 | Z74: 3.341 | AA74: 3.691 | AB74: 5482 | AC74: 17.341005 | AD74: 0.843289 | AE74: TSE | AF74: Materials
A75: Aichi Tokei Denki Co., Ltd. (TSE:7723) | B75: 4241622 | C75: 愛知時計電機株式会社 | D75: Electronic Equipment and Instruments | E75: 15382378 | F75: 3003 | G75: 3288 | H75: 3982 | I75: 3618 | J75: 3941 | K75: NA | L75: NA | M75: 4192 | N75: 3115 | O75: 1876 | P75: 1742 | Q75: 1856 | R75: -2423 | S75: 2589 | T75: -683 | U75: -1092 | V75: 738 | W75: 9.237 | X75: 8.016 | Y75: 9.394 | Z75: 7.689 | AA75: 7.769 | AB75: 7723 | AC75: 10.399344 | AD75: 0.840381 | AE75: TSE | AF75: Technology Hardware and Equipment
A76: Aida Engineering, Ltd. (TSE:6118) | B76: 4992157 | C76: アイダエンジニアリング株式会社 | D76: Machinery and Supplies and Components: Industrial | E76: 54303137 | F76: 3723 | G76: 2506 | H76: 1540 | I76: 3615 | J76: 5531 | K76: 6000 | L76: 7000 | M76: 7263 | N76: 5905 | O76: -1129 | P76: 3169 | Q76: 6512 | R76: -1921 | S76: -2828 | T76: -1884 | U76: -1988 | V76: -1830 | W76: 1.775 | X76: 1.158 | Y76: 1.653 | Z76: 3.502 | AA76: 6.147 | AB76: 6118 | AC76: 9.887822 | AD76: 0.623597 | AE76: TSE | AF76: Capital Goods
A77: Aida Sekkei Co.,Ltd. (TSE:2990) | B77: 7805311 | D77: Diversified Real Estate Activities | E77: 36759726 | F77: 1774 | G77: 1731 | H77: -1283 | I77: 807 | J77: -704 | K77: NA | L77: NA | M77: 9300 | N77: 3885 | O77: -17929 | P77: -11748 | Q77: 13868 | R77: 121 | S77: -636 | T77: -668 | U77: 9166 | V77: 1855 | W77: 7.142 | X77: 6.585 | Y77: -16.439 | Z77: 12.184 | AA77: -4.949 | AB77: 2990 | AC77: NM | AD77: NA | AE77: TSE | AF77: Real Estate Management and Development
A78: Aidma Holdings, Inc. (TSE:7373) | B78: 19083095 | C78: 株式会社アイドマ・ホールディングス | D78: Diversified Support Services | E78: 14863020 | F78: 830 | G78: 1639 | H78: 2209 | I78: 2468 | J78: 3103 | K78: 4150 | L78: 5050 | M78: 1377 | N78: 1742 | O78: 2181 | P78: 1194 | Q78: 2479 | R78: -150 | S78: -1627 | T78: -812 | U78: -1074 | V78: -799 | W78: 27.042 | X78: 29.422 | Y78: 27.274 | Z78: 23.663 | AA78: 28.129 | AB78: 7373 | AC78: 21.923046 | AD78: 5.686503 | AE78: TSE | AF78: Commercial and Professional Services
A79: Aidma Marketing Communication Corporation (TSE:9466) | B79: 4989724 | C79: 株式会社アイドマ マーケティング コミュニケーション | D79: Advertising | E79: 13079009 | F79: 213 | G79: 234 | H79: 318 | I79: 302 | J79: 360 | K79: NA | L79: NA | M79: 372 | N79: 238 | O79: 367 | P79: 299 | Q79: 232 | R79: -373 | S79: 126 | T79: 55 | U79: -61 | V79: -143 | W79: -11.394 | X79: 1.922 | Y79: -4.357 | Z79: 5.43 | AA79: 15.124 | AB79: 9466 | AC79: 6.498314 | AD79: 0.968664 | AE79: TSE | AF79: Media and Entertainment
A80: Aiful Corporation (TSE:8515) | B80: 4210214 | C80: アイフル株式会社 | D80: Specialty Finance: Consumer Focused | E80: 478830198 | F80: 17484 | G80: 11239 | H80: 23722 | I80: 21064 | J80: 25301 | K80: 32328.227 | L80: 40752.88 | M80: 20280 | N80: -15628 | O80: -70589 | P80: -74208 | Q80: -82874 | R80: -9274 | S80: -2218 | T80: -8947 | U80: -12762 | V80: -35099 | W80: 12.866 | X80: 8.571 | Y80: 13.654 | Z80: 11.287 | AA80: 10.449 | AB80: 8515 | AC80: 9.553872 | AD80: 0.651818 | AE80: TSE | AF80: Financial Services
A81: Aigan Co.,Ltd. (TSE:9854) | B81: 4242351 | C81: 愛眼株式会社 | D81: Other Specialty Retail | E81: 19407013 | F81: -521 | G81: -585 | H81: -475 | I81: -123 | J81: -128 | K81: NA | L81: NA | M81: -229 | N81: -358 | O81: -97 | P81: -87 | Q81: -155 | R81: -79 | S81: 273 | T81: -16 | U81: -166 | V81: 94 | W81: -4.022 | X81: -5.203 | Y81: -6.407 | Z81: -1.493 | AA81: 0.025 | AB81: 9854 | AC81: 52.895149 | AD81: 0.274712 | AE81: TSE | AF81: Consumer Discretionary Distribution and Retail
A82: AIMECHATEC, Ltd. (TSE:6227) | B82: 13018487 | C82: ＡＩメカテック株式会社 | D82: Electronic Manufacturing Services | E82: 6191457 | F82: 1011 | G82: 736 | H82: 581 | I82: 261 | J82: 2095 | K82: 2750 | L82: 3400 | M82: 1609 | N82: 698 | O82: -692 | P82: -1131 | Q82: 1526 | R82: -575 | S82: -340 | T82: -1130 | U82: -889 | V82: -2482 | W82: 9.771 | X82: 6.143 | Y82: 14.011 | Z82: 1.113 | AA82: 3.09 | AB82: 6227 | AC82: 88.099631 | AD82: 2.722554 | AE82: TSE | AF82: Semiconductors and Semiconductor Equipment
A83: Aiming Inc. (TSE:3911) | B83: 4972425 | C83: 株式会社 Aiming (エイミング) | D83: Interactive Home Entertainment | E83: 46668200 | F83: NA | G83: 400 | H83: -1309 | I83: -553 | J83: -553 | K83: NA | L83: NA | M83: NA | N83: -350 | O83: -1153 | P83: -964 | Q83: -964 | R83: NA | S83: -262 | T83: -695 | U83: -215 | V83: -215 | W83: NA | X83: NA | Y83: -18.718 | Z83: -7.38 | AA83: -7.38 | AB83: 3911 | AC83: 5.692698 | AD83: 1.467342 | AE83: TSE | AF83: Media and Entertainment
A84: Ain Holdings Inc. (TSE:9627) | B84: 4913588 | C84: 株式会社アインホールディングス | D84: Drug Retail | E84: 35073225 | F84: 10751 | G84: 15134 | H84: 15957 | I84: 20337 | J84: 16871 | K84: 28029.833 | L84: 33119 | M84: 14928 | N84: 26156 | O84: 20267 | P84: 23023 | Q84: 23146 | R84: -9493 | S84: -13943 | T84: -22292 | U84: -15748 | V84: -65920 | W84: 5.897 | X84: 6.047 | Y84: 7.528 | Z84: 8.71 | AA84: 6.667 | AB84: 9627 | AC84: 24.462328 | AD84: 1.645848 | AE84: TSE | AF84: Consumer Staples Distribution and Retail
A85: AINAVO HOLDINGS Co.,Ltd. (TSE:7539) | B85: 4546296 | C85: 株式会社アイナボホールディングス | D85: Homebuilding Producers | E85: 23231428 | F85: 1903 | G85: 1899 | H85: 1770 | I85: 2171 | J85: 2171 | K85: NA | L85: NA | M85: 1941 | N85: 395 | O85: 1677 | P85: 2825 | Q85: 2825 | R85: -364 | S85: 388 | T85: -2876 | U85: -641 | V85: -641 | W85: 6.053 | X85: 7.254 | Y85: 5.377 | Z85: 5.171 | AA85: 5.171 | AB85: 7539 | AC85: 9.779817 | AD85: 0.642011 | AE85: TSE | AF85: Consumer Durables and Apparel
A86: Aiphone Co.,Ltd. (TSE:6718) | B86: 4250476 | C86: アイホン株式会社 | D86: Communications Equipment | E86: 16366109 | F86: 3623 | G86: 5538 | H86: 3760 | I86: 5227 | J86: 3815 | K86: 3885 | L86: 4580 | M86: 3115 | N86: 1872 | O86: -4781 | P86: 9056 | Q86: 5717 | R86: -1296 | S86: 3729 | T86: -2533 | U86: -58 | V86: -729 | W86: 5.987 | X86: 7.812 | Y86: 5.124 | Z86: 7.534 | AA86: 5.497 | AB86: 6718 | AC86: 16.595923 | AD86: 0.688883 | AE86: TSE | AF86: Technology Hardware and Equipment
A87: Air Water Inc. (TSE:4088) | B87: 6333663 | C87: エア・ウォーター株式会社 | D87: Industrial Gases | E87: 229156684 | F87: 47458 | G87: 61264 | H87: 54018 | I87: 64553 | J87: 66424 | K87: 83293.167 | L87: 89816 | M87: 76601 | N87: 71572 | O87: 56953 | P87: 79625 | Q87: 93236 | R87: -52699 | S87: -53154 | T87: -71135 | U87: -97966 | V87: -62166 | W87: 8.384 | X87: 11.715 | Y87: 9.916 | Z87: 9.664 | AA87: 9.644 | AB87: 4088 | AC87: 10.274097 | AD87: 1.009353 | AE87: TSE | AF87: Materials
A88: airCloset, Inc. (TSE:9557) | B88: 5295777 | C88: 株式会社エアークローゼット | D88: Other Specialty Retail | E88: 8236200 | F88: 39 | G88: -52 | H88: -188 | I88: -35 | J88: 102 | K88: NA | L88: NA | M88: NA | N88: 156 | O88: 479 | P88: 802 | Q88: 1060 | R88: NA | S88: -1029 | T88: -907 | U88: -778 | V88: -1389 | W88: -358.333 | X88: -208.264 | Y88: -80.546 | Z88: -9.934 | AA88: 4.327 | AB88: 9557 | AC88: 122.90104 | AD88: 5.141926 | AE88: TSE | AF88: Consumer Discretionary Distribution and Retail
A89: Airman Corporation (TSE:6364) | B89: 4992525 | C89: 株式会社ＡＩＲＭＡＮ | D89: Machinery and Supplies and Components: Industrial | E89: 27287124 | F89: 2490 | G89: 3570 | H89: 4842 | I89: 6188 | J89: 6918 | K89: 6800 | L89: 7300 | M89: 4099 | N89: 2276 | O89: 2869 | P89: 3970 | Q89: 3910 | R89: -2017 | S89: -615 | T89: -867 | U89: -2757 | V89: -1084 | W89: 6.631 | X89: 9.024 | Y89: 11.509 | Z89: 14.252 | AA89: 12.273 | AB89: 6364 | AC89: 10.474621 | AD89: 1.21855 | AE89: TSE | AF89: Capital Goods
A90: Airport Facilities Co., Ltd. (TSE:8864) | B90: 6333838 | C90: 空港施設株式会社 | D90: Real Estate Operating and Management | E90: 50288468 | F90: 3832 | G90: 3281 | H90: 2504 | I90: 3183 | J90: 4470 | K90: 4725 | L90: 5205 | M90: 4758 | N90: 8467 | O90: 2017 | P90: 784 | Q90: 5239 | R90: -2704 | S90: -449 | T90: 1198 | U90: -3831 | V90: -3419 | W90: -1.405 | X90: 1.616 | Y90: 2.826 | Z90: 3.613 | AA90: 4.258 | AB90: 8864 | AC90: 27.8141 | AD90: 0.851192 | AE90: TSE | AF90: Real Estate Management and Development
A91: Airtech Japan, Ltd. (TSE:6291) | B91: 4992324 | C91: 日本エアーテック株式会社 | D91: Machinery and Supplies and Components: Industrial | E91: 10093083 | F91: NA | G91: NA | H91: NA | I91: NA | J91: 37.564 | K91: NA | L91: NA | M91: NA | N91: NA | O91: NA | P91: NA | Q91: 103.638 | R91: NA | S91: NA | T91: NA | U91: NA | V91: -52.806 | W91: NA | X91: NA | Y91: NA | Z91: NA | AA91: 0.332 | AB91: 6291 | AC91: NM | AD91: 1.317534 | AE91: TSE | AF91: Capital Goods
A92: AirTrip Corp. (TSE:6191) | B92: 4916191 | C92: 株式会社エアトリ | D92: Hotels, Resorts and Cruise Lines | E92: 22397656 | F92: 2404 | G92: 1201 | H92: 2703 | I92: 3428 | J92: 3428 | K92: 2000 | L92: 2500 | M92: 3630 | N92: 2807 | O92: 4117 | P92: 2271 | Q92: 2271 | R92: -1715 | S92: -952 | T92: -583 | U92: -3629 | V92: -3629 | W92: 47.105 | X92: 18.023 | Y92: 9.485 | Z92: 14.576 | AA92: 14.576 | AB92: 6191 | AC92: 14.921674 | AD92: NA | AE92: TSE | AF92: Consumer Services
A93: Air-U Ltd. (TSE:5135) | B93: 108019790 | D93: Wireless Telecommunication Services | E93: 30000000 | F93: 681 | G93: 1152 | H93: 1707 | I93: 1943 | J93: 1943 | K93: NA | L93: NA | M93: NA | N93: 967 | O93: 1364 | P93: 1253 | Q93: 1253 | R93: NA | S93: 56 | T93: -426 | U93: -281 | V93: -281 | W93: 43.756 | X93: 44.37 | Y93: 43.543 | Z93: 33.498 | AA93: 33.498 | AB93: 5135 | AC93: 3.893495 | AD93: NA | AE93: TSE | AF93: Telecommunication Services
A94: Aisan Industry Co., Ltd. (TSE:7283) | B94: 4554421 | C94: 愛三工業株式会社 | D94: Automotive Parts and Equipment | E94: 57027755 | F94: 4957 | G94: 9810 | H94: 13633 | I94: 15499 | J94: 18340 | K94: 20000 | L94: 22000 | M94: 17761 | N94: 13544 | O94: 20269 | P94: 38627 | Q94: 28222 | R94: -6785 | S94: -6955 | T94: -29599 | U94: -9664 | V94: -20128 | W94: 4.397 | X94: 7.814 | Y94: 8.65 | Z94: 9.95 | AA94: 9.964 | AB94: 7283 | AC94: 9.744712 | AD94: 0.902124 | AE94: TSE | AF94: Automobiles and Components
A95: Aisan Technology Co.,Ltd. (TSE:4667) | B95: 4546303 | C95: アイサンテクノロジー株式会社 | D95: Application Software | E95: 5268557 | F95: 245 | G95: 257 | H95: 331 | I95: 450 | J95: 449 | K95: NA | L95: NA | M95: 408 | N95: 586 | O95: 391 | P95: -240 | Q95: 933 | R95: -126 | S95: -201 | T95: -209 | U95: -125 | V95: -174 | W95: 3.139 | X95: 3.515 | Y95: 4.038 | Z95: 5.376 | AA95: 4.772 | AB95: 4667 | AC95: 28.501022 | AD95: 1.303164 | AE95: TSE | AF95: Software and Services
A96: Aisin Corporation (TSE:7259) | B96: 4251532 | C96: 株式会社アイシン | D96: Automotive Parts and Equipment | E96: 737750935 | F96: 145044 | G96: 179056 | H96: 74555 | I96: 146503 | J96: 202372 | K96: 222387.19 | L96: 262715.84 | M96: 343314 | N96: 193343 | O96: 237970 | P96: 499740 | Q96: 339870 | R96: -138175 | S96: -204952 | T96: -186857 | U96: -93153 | V96: -146948 | W96: 6.196 | X96: 8.363 | Y96: 2.403 | Z96: 5.135 | AA96: 5.36 | AB96: 7259 | AC96: 12.364477 | AD96: 1.004884 | AE96: TSE | AF96: Automobiles and Components
A97: AIT Corporation (TSE:9381) | B97: 4995166 | C97: 株式会社エーアイテイー | D97: Air Freight and Logistics | E97: 23493592 | F97: 2305 | G97: 3582 | H97: 5289 | I97: 4329 | J97: 4075 | K97: NA | L97: NA | M97: 1521 | N97: 3772 | O97: 5321 | P97: 3174 | Q97: 3228 | R97: -300 | S97: 396 | T97: 167 | U97: -201 | V97: -1878 | W97: 14.734 | X97: 18.269 | Y97: 24.677 | Z97: 17.781 | AA97: 16.914 | AB97: 9381 | AC97: 15.046245 | AD97: 2.452063 | AE97: TSE | AF97: Transportation
A98: Aizawa Securities Group Co., Ltd. (TSE:8708) | B98: 4207686 | C98: アイザワ証券グループ株式会社 | D98: Investment Banks, Brokers and Capital Markets | E98: 31139226 | F98: NA | G98: NA | H98: NA | I98: NA | J98: NA | K98: NA | L98: NA | M98: -1618 | N98: -3930 | O98: -9487 | P98: 8447 | Q98: -5759 | R98: 4111 | S98: 4749 | T98: 474 | U98: 1478 | V98: 1180 | W98: 8.364 | X98: 4.926 | Y98: -4.289 | Z98: 5.115 | AA98: 5.88 | AB98: 8708 | AC98: 14.848229 | AD98: 0.876009 | AE98: TSE | AF98: Financial Services
A99: Ajinomoto Co., Inc. (TSE:2802) | B99: 4250477 | C99: 味の素株式会社 | D99: Packaged Foods and Meats Producers | E99: 972148252 | F99: 105844 | G99: 121918 | H99: 130601 | I99: 141110 | J99: 146871 | K99: 182660.53 | L99: 209599.4 | M99: 165650 | N99: 145576 | O99: 117640 | P99: 168074 | Q99: 209898 | R99: -66247 | S99: -61567 | T99: -30087 | U99: -132434 | V99: -77382 | W99: 10.521 | X99: 11.399 | Y99: 12.82 | Z99: 11.954 | AA99: 9.518 | AB99: 2802 | AC99: 50.342518 | AD99: 4.925881 | AE99: TSE | AF99: Food, Beverage and Tobacco
A100: AJIS Co., Ltd. (TSE:4659) | B100: 6342366 | C100: 株式会社エイジス | D100: Diversified Support Services | E100: 8433724 | F100: 4721 | G100: 3936 | H100: 2804 | I100: 2522 | J100: 3028 | K100: NA | L100: NA | M100: 4047 | N100: 1533 | O100: 2921 | P100: 1978 | Q100: 3126 | R100: -309 | S100: 427 | T100: -556 | U100: -3279 | V100: -325 | W100: 18.003 | X100: 11.515 | Y100: 8.741 | Z100: 8.316 | AA100: 8.672 | AB100: 4659 | AC100: 11.368342 | AD100: 0.978042 | AE100: TSE | AF100: Commercial and Professional Services
A101: Akasaka Diesels Limited (TSE:6022) | B101: 4244732 | C101: 株式会社赤阪鐵工所 | D101: Machinery and Equipment: Construction and Heavy Transportation | E101: 1504698 | F101: NA | G101: NA | H101: NA | I101: NA | J101: 848.443 | K101: NA | L101: NA | M101: NA | N101: NA | O101: NA | P101: NA | Q101: 637.884 | R101: NA | S101: NA | T101: NA | U101: NA | V101: -1239.844 | W101: NA | X101: NA | Y101: NA | Z101: NA | AA101: 6.272 | AB101: 6022 | AC101: 24.737225 | AD101: 1.005505 | AE101: TSE | AF101: Capital Goods
A102: Akatsuki Corp. (TSE:8737) | B102: 4298525 | C102: 株式会社あかつき本社 | D102: Investment Banks, Brokers and Capital Markets | E102: 30268061 | F102: 2591 | G102: 1568 | H102: 1803 | I102: 3419 | J102: 3725 | K102: NA | L102: NA | M102: 6852 | N102: -4612 | O102: -474 | P102: 817 | Q102: -3348 | R102: -1436 | S102: -950 | T102: 51 | U102: -771 | V102: -298 | W102: 10.491 | X102: 6.898 | Y102: 6.339 | Z102: 16.17 | AA102: 14.922 | AB102: 8737 | AC102: 6.068371 | AD102: 0.885886 | AE102: TSE | AF102: Financial Services
A103: Akatsuki Eazima Co., Ltd. (TSE:1997) | B103: 4990415 | C103: 暁飯島工業株式会社 | D103: Construction and Engineering | E103: 2024415 | F103: NA | G103: NA | H103: NA | I103: NA | J103: 296.711 | K103: NA | L103: NA | M103: NA | N103: NA | O103: NA | P103: NA | Q103: 1042.816 | R103: NA | S103: NA | T103: NA | U103: NA | V103: -109.123 | W103: NA | X103: NA | Y103: NA | Z103: NA | AA103: 12.196 | AB103: 1997 | AC103: 31.067457 | AD103: 3.935338 | AE103: TSE | AF103: Capital Goods
...
